Workbook

Sheet Portfolio Management
B2: Stock Returns | E2: Stock Return Statistics | I2: Portfolio Weighting | O2: Capital Allocation Line
B3: CI | C3: EBAY | F3: CI | G3: EBAY | I3: CI | J3: EBAY | K3: Port Return | L3: Port St Dev | M3: Sharpe Ratio | O3: Weight | P3: Return | Q3: St Dev
B4: 0.066588043 | C4: 0.048221111 | E4: average | F4: =AVERAGE(B4:B62) -> 0.005667299 | G4: =AVERAGE(C4:C62) -> 0.0049795291 | I4: 1 | J4: 0 | K4: =(I4*$F$4)+(J4*$G$4) -> 0.005667299 | L4: =((I4^2*$F$5^2)+(J4^2*$G$5^2)+(2*I4*J4*$F$6))^(1/2) -> 0.079262927 | M4: =(K4-$F$7)/L4 -> 0.042188218 | O4: 0 | P4: =(O4*$K$11)+((1-O4)*$F$7) -> 0.0023233374 | Q4: =(O4*$L$11) -> 0
B5: 0.046878543 | C5: -0.042323139 | E5: St Dev | F5: =_xlfn.STDEV.P(B4:B62) -> 0.079262927 | G5: =_xlfn.STDEV.P(C4:C62) -> 0.090122992 | I5: 0.95 | J5: 0.05 | K5: =(I5*$F$4)+(J5*$G$4) -> 0.0056329105 | L5: =((I5^2*$F$5^2)+(J5^2*$G$5^2)+(2*I5*J5*$F$6))^(1/2) -> 0.076311417 | M5: =(K5-$F$7)/L5 -> 0.043369306 | O5: 1 | P5: =(O5*$K$11)+((1-O5)*$F$7) -> 0.0054265796 | Q5: =(O5*$L$11) -> 0.065472913
B6: 0.056152277 | C6: 0.081950207 | E6: Covariance | F6: =_xlfn.COVARIANCE.P(B4:B62,C4:C62) -> 0.0014007365 | I6: 0.9 | J6: 0.1 | K6: =(I6*$F$4)+(J6*$G$4) -> 0.0055985221 | L6: =((I6^2*$F$5^2)+(J6^2*$G$5^2)+(2*I6*J6*$F$6))^(1/2) -> 0.073636061 | M6: =(K6-$F$7)/L6 -> 0.044477999 | O6: 1.5 | P6: =(O6*$K$11)+((1-O6)*$F$7) -> 0.0069782007 | Q6: =(O6*$L$11) -> 0.09820937
B7: -0.21654422 | C7: -0.025988701 | E7: risk free | F7: ='10YR Treasury'!E69 -> 0.0023233374 | I7: 0.85 | J7: 0.15 | K7: =(I7*$F$4)+(J7*$G$4) -> 0.0055641336 | L7: =((I7^2*$F$5^2)+(J7^2*$G$5^2)+(2*I7*J7*$F$6))^(1/2) -> 0.071267967 | M7: =(K7-$F$7)/L7 -> 0.045473392
B8: 0.068766466 | C8: 0.095185651 | I8: 0.8 | J8: 0.2 | K8: =(I8*$F$4)+(J8*$G$4) -> 0.0055297451 | L8: =((I8^2*$F$5^2)+(J8^2*$G$5^2)+(2*I8*J8*$F$6))^(1/2) -> 0.069238669 | M8: =(K8-$F$7)/L8 -> 0.046309494
B9: -0.10569648 | C9: -0.13215093 | I9: 0.75 | J9: 0.25 | K9: =(I9*$F$4)+(J9*$G$4) -> 0.0054953566 | L9: =((I9^2*$F$5^2)+(J9^2*$G$5^2)+(2*I9*J9*$F$6))^(1/2) -> 0.067578694 | M9: =(K9-$F$7)/L9 -> 0.046938155
B10: -0.039732053 | C10: 0.088158501 | I10: 0.7 | J10: 0.3 | K10: =(I10*$F$4)+(J10*$G$4) -> 0.0054609681 | L10: =((I10^2*$F$5^2)+(J10^2*$G$5^2)+(2*I10*J10*$F$6))^(1/2) -> 0.066315781 | M10: =(K10-$F$7)/L10 -> 0.047313485
B11: 0.0357528 | C11: 0.063331649 | E11: Complete Portfolio | I11: 0.65 | J11: 0.35 | K11: =(I11*$F$4)+(J11*$G$4) -> 0.0054265796 | L11: =((I11^2*$F$5^2)+(J11^2*$G$5^2)+(2*I11*J11*$F$6))^(1/2) -> 0.065472913 | M11: =(K11-$F$7)/L11 -> 0.047397344
B12: 0.049151181 | C12: 0.033986693 | E12: 3 | F12: ='Portfolio Management'!K11 -> 0.0054265796 | I12: 0.6 | J12: 0.4 | K12: =(I12*$F$4)+(J12*$G$4) -> 0.0053921911 | L12: =((I12^2*$F$5^2)+(J12^2*$G$5^2)+(2*I12*J12*$F$6))^(1/2) -> 0.065066414 | M12: =(K12-$F$7)/L12 -> 0.047164943
B13: -0.038301466 | C13: -0.014333582 | E13: St Dev of Optimal Risky Portfolio | F13: ='Portfolio Management'!L11 -> 0.065472913 | I13: 0.55 | J13: 0.45 | K13: =(I13*$F$4)+(J13*$G$4) -> 0.0053578026 | L13: =((I13^2*$F$5^2)+(J13^2*$G$5^2)+(2*I13*J13*$F$6))^(1/2) -> 0.06510446 | M13: =(K13-$F$7)/L13 -> 0.046609176
B14: -0.037469502 | C14: 0.054138374 | E14: Risk-free rate | F14: ='Portfolio Management'!F7 -> 0.0023233374 | I14: 0.5 | J14: 0.5 | K14: =(I14*$F$4)+(J14*$G$4) -> 0.0053234141 | L14: =((I14^2*$F$5^2)+(J14^2*$G$5^2)+(2*I14*J14*$F$6))^(1/2) -> 0.065586276 | M14: =(K14-$F$7)/L14 -> 0.045742447
B15: -0.020745842 | C15: -0.029297633 | E15: Risk Aversion | F15: 3 | I15: 0.45 | J15: 0.55 | K15: =(I15*$F$4)+(J15*$G$4) -> 0.0052890256 | L15: =((I15^2*$F$5^2)+(J15^2*$G$5^2)+(2*I15*J15*$F$6))^(1/2) -> 0.066502217 | M15: =(K15-$F$7)/L15 -> 0.044595329
B16: 0.079184838 | C16: 0.10876532 | E16: Investment | F16: 10000 | I16: 0.4 | J16: 0.6 | K16: =(I16*$F$4)+(J16*$G$4) -> 0.0052546371 | L16: =((I16^2*$F$5^2)+(J16^2*$G$5^2)+(2*I16*J16*$F$6))^(1/2) -> 0.067834701 | M16: =(K16-$F$7)/L16 -> 0.043212392
B17: 0.10318122 | C17: 0.13134518 | I17: 0.35 | J17: 0.65 | K17: =(I17*$F$4)+(J17*$G$4) -> 0.0052202486 | L17: =((I17^2*$F$5^2)+(J17^2*$G$5^2)+(2*I17*J17*$F$6))^(1/2) -> 0.069559794 | M17: =(K17-$F$7)/L17 -> 0.041646346
B18: 0.001129268 | C18: -0.062089116 | I18: 0.3 | J18: 0.7 | K18: =(I18*$F$4)+(J18*$G$4) -> 0.0051858601 | L18: =((I18^2*$F$5^2)+(J18^2*$G$5^2)+(2*I18*J18*$F$6))^(1/2) -> 0.071649143 | M18: =(K18-$F$7)/L18 -> 0.039951947
B19: 0.12582297 | C19: 0.054103622 | I19: 0.25 | J19: 0.75 | K19: =(I19*$F$4)+(J19*$G$4) -> 0.0051514716 | L19: =((I19^2*$F$5^2)+(J19^2*$G$5^2)+(2*I19*J19*$F$6))^(1/2) -> 0.07407193 | M19: =(K19-$F$7)/L19 -> 0.038180917
B20: -0.17569418 | C20: 0.049200194 | E20: Optimal Allocation Computation | F20: =(F12-F14)/(F15*(F13)^2) -> 0.24130765 | I20: 0.2 | J20: 0.8 | K20: =(I20*$F$4)+(J20*$G$4) -> 0.0051170831 | L20: =((I20^2*$F$5^2)+(J20^2*$G$5^2)+(2*I20*J20*$F$6))^(1/2) -> 0.076796605 | M20: =(K20-$F$7)/L20 -> 0.036378506
B21: 0.070464913 | C21: -0.12388478 | E21: Optimal Risky Portfolio Allocation | F21: =F20 -> 0.24130765 | I21: 0.15 | J21: 0.85 | K21: =(I21*$F$4)+(J21*$G$4) -> 0.0050826946 | L21: =((I21^2*$F$5^2)+(J21^2*$G$5^2)+(2*I21*J21*$F$6))^(1/2) -> 0.079792246 | M21: =(K21-$F$7)/L21 -> 0.034581772
B22: 0.038042532 | C22: -0.021320027 | E22: Optimal T-Notes Allocation | F22: =1-F21 -> 0.75869235 | I22: 0.1 | J22: 0.9 | K22: =(I22*$F$4)+(J22*$G$4) -> 0.0050483061 | L22: =((I22^2*$F$5^2)+(J22^2*$G$5^2)+(2*I22*J22*$F$6))^(1/2) -> 0.083029532 | M22: =(K22-$F$7)/L22 -> 0.032819272
B23: -0.067732832 | C23: 0.011547857 | I23: 0.05 | J23: 0.95 | K23: =(I23*$F$4)+(J23*$G$4) -> 0.0050139176 | L23: =((I23^2*$F$5^2)+(J23^2*$G$5^2)+(2*I23*J23*$F$6))^(1/2) -> 0.086481328 | M23: =(K23-$F$7)/L23 -> 0.03111169
B24: 0.045272789 | C24: -0.004044035 | E24: Optimal Risky Portfolio | F24: =F16*F21 -> 2413.0765 | I24: 0 | J24: 1 | K24: =(I24*$F$4)+(J24*$G$4) -> 0.0049795291 | L24: =((I24^2*$F$5^2)+(J24^2*$G$5^2)+(2*I24*J24*$F$6))^(1/2) -> 0.090122992 | M24: =(K24-$F$7)/L24 -> 0.029472965
B25: 0.12153049 | C25: 0.042515104 | E25: T-Notes | F25: =F16*F22 -> 7586.9235
B26: -0.023393939 | C26: -0.085066604
B27: -0.012831142 | C27: 0.038983416 | E27: Optimal Risky Portfolio Weights
B28: -0.13756139 | C28: -0.028686688 | E28: Ebay | F28: ='Portfolio Management'!J11 -> 0.35 | G28: =F24*F28 -> 844.57678
B29: -0.085118048 | C29: -0.078431373 | E29: Cigna | F29: ='Portfolio Management'!I11 -> 0.65 | G29: =F24*F29 -> 1568.4997
B30: -0.049957369 | C30: 0.16222222
B31: 0.0116996 | C31: -0.10103689 | E31: Asset | F31: Allocation | G31: Weight
B32: 0.016281193 | C32: 0.12746386 | E32: T-Notes | F32: =F25 -> 7586.9235 | G32: =F32/$F$35 -> 0.75869235
B33: 0.1374478 | C33: 0.076054217 | E33: Cigna | F33: =G29 -> 1568.4997 | G33: =F33/$F$35 -> 0.15684997
B34: -0.01656983 | C34: -0.20483564 | E34: eBay | F34: =G28 -> 844.57678 | G34: =F34/$F$35 -> 0.084457678
B35: 0.028506915 | C35: -0.096505073 | E35: Total | F35: =SUM(F32:F34) -> 10000 | G35: =SUM(G32:G34) -> 1
B36: 0.038858222 | C36: 0.14312153
B37: -0.014471397 | C37: -0.17326614
B38: 0.080822377 | C38: -0.061975864
B39: 0.024474249 | C39: -0.10708783
B40: 0.012502596 | C40: 0.050278358
B41: 0.031294692 | C41: -0.10038469
B42: -0.0014763352 | C42: -0.10704178
B43: 0.1679674 | C43: -0.017142857
B44: -0.11334028 | C44: -0.13424009
B45: 0.058226071 | C45: 0.091892596
B46: -0.051687292 | C46: -0.10406201
B47: -0.084825859 | C47: 0.11323453
... B62: 0.0055814898 | C62: 0.12844639

Sheet Excess Return Analysis
B2: Stock Excess Returns | H2: Correlation
B3: CI | C3: KMB | D3: EBAY | E3: CAT | F3: SPX | I3: CI | J3: KMB | K3: EBAY | L3: CAT | M3: SPX
B4: {='CI - Stock PX'!G8:G66} -> 0.063083627 | C4: {='KMB - Stock PX'!G8:G66} -> 0.0067409137 | D4: {='EBAY - Stock PX'!G8:G66} -> 0.044716695 | E4: {='CAT - Stock PX'!G8:G66} -> -0.046409207 | F4: {='SPX - Tot Ret'!D2:D60} -> -0.061058296 | H4: CI | I4: =CORREL(_xlfn.ANCHORARRAY(B4),_xlfn.ANCHORARRAY(B4)) -> 1 | J4: =CORREL(_xlfn.ANCHORARRAY(B4),_xlfn.ANCHORARRAY(C4)) -> 0.22710209 | K4: =CORREL(_xlfn.ANCHORARRAY(B4),_xlfn.ANCHORARRAY(D4)) -> 0.19707199 | L4: =CORREL(_xlfn.ANCHORARRAY(B4),_xlfn.ANCHORARRAY(E4)) -> 0.38248323 | M4: =CORREL(_xlfn.ANCHORARRAY(B4),_xlfn.ANCHORARRAY(F4)) -> 0.22033806
B5: 0.04337171 | C5: 0.081275928 | D5: -0.045829972 | E5: -0.087530674 | F5: -0.014447897 | H5: KMB | I5: 0.22710209 | J5: 1 | K5: =CORREL(_xlfn.ANCHORARRAY(C4),_xlfn.ANCHORARRAY(D4)) -> 0.33701044 | L5: =CORREL(_xlfn.ANCHORARRAY(C4),_xlfn.ANCHORARRAY(E4)) -> 0.16257082 | M5: =CORREL(_xlfn.ANCHORARRAY(C4),_xlfn.ANCHORARRAY(F4)) -> 0.30229223
B6: 0.052370027 | C6: -0.021401701 | D6: 0.078167957 | E6: 0.023279571 | F6: 0.026305639 | H6: EBAY | I6: 0.19707199 | J6: 0.33701044 | K6: 1 | L6: =CORREL(_xlfn.ANCHORARRAY(D4),_xlfn.ANCHORARRAY(E4)) -> 0.60939707 | M6: =CORREL(_xlfn.ANCHORARRAY(D4),_xlfn.ANCHORARRAY(F4)) -> 0.69529735
B7: -0.22035172 | C7: -0.057414033 | D7: -0.029796201 | E7: -0.123308 | F7: -0.02563065 | H7: CAT | I7: 0.38248323 | J7: 0.16257082 | K7: 0.60939707 | L7: 1 | M7: =CORREL(_xlfn.ANCHORARRAY(E4),_xlfn.ANCHORARRAY(F4)) -> 0.68508414
B8: 0.065292716 | C8: 0.033627075 | D8: 0.091711901 | E8: 0.066704281 | F8: 0.054195856 | H8: SPX | I8: 0.22033806 | J8: 0.30229223 | K8: 0.69529735 | L8: 0.68508414 | M8: 1
B9: -0.10926682 | C9: -0.073029269 | D9: -0.13572126 | E9: -0.039347988 | F9: -0.0099957059
B10: -0.042882803 | C10: -0.011234374 | D10: 0.085007751 | E10: 0.086386988 | F10: 0.019797032 | H10: Covarience
B11: 0.032499966 | C11: 0.063178799 | D11: 0.060078816 | E11: 0.020588784 | F11: 0.022324906 | I11: CI | J11: KMB | K11: EBAY | L11: CAT | M11: SPX
B12: 0.045793181 | C12: -0.035716386 | D12: 0.030628693 | E12: 0.038384182 | F12: 0.011194611 | H12: CI | I12: =VARP('Excess Return Analysis'!$B$4:$B$62) -> 0.0062842314 | J12: 0.00096292944 | K12: 0.0014092895 | L12: 0.0026455691 | M12: 0.00080819174
B13: -0.041964882 | C13: 0.040232724 | D13: -0.017996998 | E13: -0.019934807 | F13: 0.033508043 | H13: KMB | I13: 0.00096292944 | J13: =VARP('Excess Return Analysis'!$C$4:$C$62) -> 0.002860846 | K13: 0.0016260722 | L13: 0.00075870067 | M13: 0.00074812302
B14: -0.041218252 | C14: -0.027979808 | D14: 0.050389624 | E14: 0.0040794433 | F14: 0.045820851 | H14: EBAY | I14: 0.0014092895 | J14: 0.0016260722 | K14: =VARP('Excess Return Analysis'!$D$4:$D$62) -> 0.0081376401 | L14: 0.0047965639 | M14: 0.0029021417
B15: -0.024645676 | C15: 0.039753576 | D15: -0.033197466 | E15: -0.094887418 | F15: -0.043422053 | H15: CAT | I15: 0.0026455691 | J15: 0.00075870067 | K15: 0.0047965639 | L15: =VARP('Excess Return Analysis'!$E$4:$E$62) -> 0.0076130951 | M15: 0.0027658163
B16: 0.075684588 | C16: 0.068491785 | D16: 0.10526507 | E16: 0.08511149 | F16: 0.030085548 | H16: SPX | I16: 0.00080819174 | J16: 0.00074812302 | K16: 0.0029021417 | L16: 0.0027658163 | M16: =VARP('Excess Return Analysis'!$F$4:$F$62) -> 0.0021409059
B17: 0.099639389 | C17: -0.0018912598 | D17: 0.12780334 | E17: 0.093326055 | F17: 0.049177143
B18: -0.0021310654 | C18: -0.017478735 | D18: -0.065349449 | E18: 0.016433974 | F18: 0.015647024
B19: 0.12259039 | C19: -0.011709232 | D19: 0.050871039 | E19: 0.14879502 | F19: 0.042355807 | H19: Stock Beta's | L19: Stock Alpha's
B20: -0.17929951 | C20: 0.029450514 | D20: 0.045594861 | E20: 0.089606217 | F20: 0.08187749 | I20: Via Data | J20: Via Slope | M20: Via Intercept
B21: 0.066355996 | C21: -0.024085513 | D21: -0.1279937 | E21: -0.20490065 | F21: -0.022473652 | H21: CI Beta | I21: =I16/F64 -> 0.37749988 | J21: =SLOPE(_xlfn.ANCHORARRAY(B4),_xlfn.ANCHORARRAY(F4)) -> 0.37749988 | L21: CI Alpha | M21: =INTERCEPT(_xlfn.ANCHORARRAY(B4),_xlfn.ANCHORARRAY(F4)) -> -0.0005103403
B22: 0.034233282 | C22: -0.059533252 | D22: -0.025129277 | E22: -0.03358947 | F22: -0.051214421 | H22: KMB Beta | I22: =J16/F64 -> 0.34944226 | J22: =SLOPE(_xlfn.ANCHORARRAY(C4),_xlfn.ANCHORARRAY(F4)) -> 0.34944226 | L22: KMB Alpha | M22: =INTERCEPT(_xlfn.ANCHORARRAY(C4),_xlfn.ANCHORARRAY(F4)) -> -0.0067336438
B23: -0.071156248 | C23: -0.0055192018 | D23: 0.0081244403 | E23: 0.048723277 | F23: -0.018035965 | H23: EBAY Beta | I23: =K16/F64 -> 1.3555671 | J23: =SLOPE(_xlfn.ANCHORARRAY(D4),_xlfn.ANCHORARRAY(F4)) -> 1.3555671 | L23: EBAY Alpha | M23: =INTERCEPT(_xlfn.ANCHORARRAY(D4),_xlfn.ANCHORARRAY(F4)) -> -0.010968099
B24: 0.041973789 | C24: -0.081842765 | D24: -0.007343035 | E24: 0.073332516 | F24: 0.030198564 | H24: CAT Beta | I24: =L16/F64 -> 1.2918906 | J24: =SLOPE(_xlfn.ANCHORARRAY(E4),_xlfn.ANCHORARRAY(F4)) -> 1.2918906 | L24: CAT Alpha | M24: =INTERCEPT(_xlfn.ANCHORARRAY(E4),_xlfn.ANCHORARRAY(F4)) -> -0.0018089424
B25: 0.11833324 | C25: 0.032424698 | D25: 0.039317854 | E25: 0.1605906 | F25: 0.060792562
B26: -0.026429439 | C26: -0.082049501 | D26: -0.088102104 | E26: -0.072294309 | F26: 0.0024761773
B27: -0.015682809 | C27: 0.062646297 | D27: 0.036131749 | E27: -0.043033485 | F27: 0.014431056
B28: -0.14045106 | C28: 0.073550511 | D28: -0.031576354 | E28: -0.049690925 | F28: 0.033864566
B29: -0.088384715 | C29: -0.042930801 | D29: -0.081698039 | E29: -0.061459111 | F29: -0.026812589
B30: -0.052879786 | C30: -0.055995257 | D30: 0.15929981 | E30: 0.052030441 | F30: 0.058161213
B31: 0.0084706 | C31: 0.0061202075 | D31: -0.10426589 | E31: 0.0099201067 | F31: -0.062667014
B32: 0.013276693 | C32: 0.079351911 | D32: 0.12445936 | E32: 0.076306866 | F32: 0.05101088
B33: 0.13407463 | C33: 0.083080312 | D33: 0.07268105 | E33: 0.24279057 | F33: 0.073956994
B34: -0.01976033 | C34: -0.12473843 | D34: -0.20802614 | E34: -0.12892185 | F34: -0.10301705
B35: 0.025846415 | C35: -0.036145444 | D35: -0.099165573 | E35: -0.082461269 | F35: -0.044321113
B36: 0.036650972 | C36: -0.036504238 | D36: 0.14091428 | E36: 0.10152802 | F36: 0.083507453
... B62: 0.0050376564 | C62: 0.020383768 | D62: 0.12790256 | E62: 0.022098304 | F62: 0.043320161
F63: =_xlfn.STDEV.P(F4:F62) -> 0.046269925 | G63: SD
F64: =F63*F63 -> 0.0021409059 | G64: Variance

Sheet DDM
B3: BASE CASE | H3: BULL CASE | N3: BEAR CASE
B4: Assumptions | H4: Assumptions | N4: Assumptions
B5: Rate of Return | C5: ='CAPM and WACC'!B5 -> 0.082102733 | H5: Rate of Return | I5: ='CAPM and WACC'!B5 -> 0.082102733 | N5: Rate of Return | O5: ='CAPM and WACC'!B5 -> 0.082102733
B6: Short term growth | C6: 0.14 | H6: Short term growth | I6: 0.16 | N6: Short term growth | O6: 0.12
B7: Mid term growth | C7: 0.08 | H7: Mid term growth | I7: 0.1 | N7: Mid term growth | O7: 0.07
B8: Long term growth | C8: 0.03 | H8: Long term growth | I8: 0.03 | N8: Long term growth | O8: 0.03
B11: Years(index) | C11: Years | D11: DPS | E11: Growth Rate | F11: Discounted | H11: Years(index) | I11: Years | J11: DPS | K11: Growth Rate | L11: Discounted | N11: Years(index) | O11: Years | P11: DPS | Q11: Growth Rate | R11: Discounted
B12: -4 | C12: 2020 | D12: 0.64 | H12: -4 | I12: 2020 | J12: 0.64 | N12: -4 | O12: 2020 | P12: 0.64
B13: -3 | C13: 2021 | D13: 0.72 | E13: =(D13-D12)/D12 -> 0.125 | H13: -3 | I13: 2021 | J13: 0.72 | K13: =(J13-J12)/J12 -> 0.125 | N13: -3 | O13: 2021 | P13: 0.72 | Q13: =(P13-P12)/P12 -> 0.125
B14: -2 | C14: 2022 | D14: 0.88 | E14: =(D14-D13)/D13 -> 0.22222222 | H14: -2 | I14: 2022 | J14: 0.88 | K14: =(J14-J13)/J13 -> 0.22222222 | N14: -2 | O14: 2022 | P14: 0.88 | Q14: =(P14-P13)/P13 -> 0.22222222
B15: -1 | C15: 2023 | D15: 1 | E15: =(D15-D14)/D14 -> 0.13636364 | H15: -1 | I15: 2023 | J15: 1 | K15: =(J15-J14)/J14 -> 0.13636364 | N15: -1 | O15: 2023 | P15: 1 | Q15: =(P15-P14)/P14 -> 0.13636364
B16: 0 | C16: 2024 | D16: 1.08 | E16: =(D16-D15)/D15 -> 0.08 | H16: 0 | I16: 2024 | J16: 1.08 | K16: =(J16-J15)/J15 -> 0.08 | N16: 0 | O16: 2024 | P16: 1.08 | Q16: =(P16-P15)/P15 -> 0.08
B17: 1 | C17: 2025 | D17: =D16*(1+E17) -> 1.2321682 | E17: =AVERAGE($E$12:$E$16) -> 0.14089646 | F17: =D17/((1+$C$5)^B17) -> 1.1386795 | H17: 1 | I17: 2025 | J17: =J16*(1+K17) -> 1.2528 | K17: =$I$6 -> 0.16 | L17: =J17/((1+$C$5)^H17) -> 1.1577459 | N17: 1 | O17: 2025 | P17: =P16*(1+Q17) -> 1.2096 | Q17: 0.12 | R17: =P17/((1+$C$5)^N17) -> 1.1178236
B18: 2 | C18: 2026 | D18: =D17*(1+E18) -> 1.4057763 | E18: =AVERAGE($E$12:$E$16) -> 0.14089646 | F18: =D18/((1+$C$5)^B18) -> 1.2005472 | H18: 2 | I18: 2026 | J18: =J17*(1+K18) -> 1.453248 | K18: =$I$6 -> 0.16 | L18: =J18/((1+$C$5)^H18) -> 1.2410885 | N18: 2 | O18: 2026 | P18: =P17*(1+Q18) -> 1.354752 | Q18: 0.12 | R18: =P18/((1+$C$5)^N18) -> 1.1569719
B19: 3 | C19: 2027 | D19: =D18*(1+E19) -> 1.6038452 | E19: =AVERAGE($E$12:$E$16) -> 0.14089646 | F19: =D19/((1+$C$5)^B19) -> 1.2657764 | H19: 3 | I19: 2027 | J19: =J18*(1+K19) -> 1.6857677 | K19: =$I$6 -> 0.16 | L19: =J19/((1+$C$5)^H19) -> 1.3304307 | N19: 3 | O19: 2027 | P19: =P18*(1+Q19) -> 1.5173222 | Q19: 0.12 | R19: =P19/((1+$C$5)^N19) -> 1.1974912
B20: 4 | C20: 2028 | D20: =D19*(1+E20) -> 1.8298214 | E20: =AVERAGE($E$12:$E$16) -> 0.14089646 | F20: =D20/((1+$C$5)^B20) -> 1.3345496 | H20: 4 | I20: 2028 | J20: =J19*(1+K20) -> 1.9554905 | K20: =$I$6 -> 0.16 | L20: =J20/((1+$C$5)^H20) -> 1.4262043 | N20: 4 | O20: 2028 | P20: =P19*(1+Q20) -> 1.6994009 | Q20: 0.12 | R20: =P20/((1+$C$5)^N20) -> 1.2394296
B21: 5 | C21: 2029 | D21: =D20*(1+E21) -> 2.0859964 | E21: 0.14 | F21: =D21/((1+$C$5)^B21) -> 1.4059539 | H21: 5 | I21: 2029 | J21: =J20*(1+K21) -> 2.268369 | K21: =$I$6 -> 0.16 | L21: =J21/((1+$C$5)^H21) -> 1.5288724 | N21: 5 | O21: 2029 | P21: =P20*(1+Q21) -> 1.818359 | Q21: 0.07 | R21: =P21/((1+$C$5)^N21) -> 1.2255673
B22: 6 | C22: 2030 | D22: =D21*(1+E22) -> 2.3780358 | E22: 0.14 | F22: =D22/((1+$C$5)^B22) -> 1.4811786 | H22: 6 | I22: 2030 | J22: =J21*(1+K22) -> 2.631308 | K22: =$I$6 -> 0.16 | L22: =J22/((1+$C$5)^H22) -> 1.6389312 | N22: 6 | O22: 2030 | P22: =P21*(1+Q22) -> 1.9456441 | Q22: 0.07 | R22: =P22/((1+$C$5)^N22) -> 1.21186
B23: 7 | C23: 2031 | D23: =D22*(1+E23) -> 2.5682787 | E23: =0.08 -> 0.08 | F23: =D23/((1+$C$5)^B23) -> 1.4783004 | H23: 7 | I23: 2031 | J23: =J22*(1+K23) -> 2.8944388 | K23: 0.1 | L23: =J23/((1+$C$5)^H23) -> 1.6660381 | N23: 7 | O23: 2031 | P23: =P22*(1+Q23) -> 2.0818392 | Q23: 0.07 | R23: =P23/((1+$C$5)^N23) -> 1.198306
B24: 8 | C24: 2032 | D24: =D23*(1+E24) -> 2.773741 | E24: 0.08 | F24: =D24/((1+$C$5)^B24) -> 1.4754278 | H24: 8 | I24: 2032 | J24: =J23*(1+K24) -> 3.1838827 | K24: 0.1 | L24: =J24/((1+$C$5)^H24) -> 1.6935932 | N24: 8 | O24: 2032 | P24: =P23*(1+Q24) -> 2.2275679 | Q24: 0.07 | R24: =P24/((1+$C$5)^N24) -> 1.1849036
B25: 9 | C25: 2033 | D25: =D24*(1+E25) -> 2.9956403 | E25: 0.08 | F25: =D25/((1+$C$5)^B25) -> 1.4725607 | H25: 9 | I25: 2033 | J25: =J24*(1+K25) -> 3.502271 | K25: 0.1 | L25: =J25/((1+$C$5)^H25) -> 1.7216042 | N25: 9 | O25: 2033 | P25: =P24*(1+Q25) -> 2.294395 | Q25: 0.03 | R25: =P25/((1+$C$5)^N25) -> 1.127851
B26: 10 | C26: 2034 | D26: =D25*(1+E26) -> 3.0855095 | E26: 0.03 | F26: =D26/((1+$C$5)^B26) -> 1.4016576 | H26: 10 | I26: 2034 | J26: =J25*(1+K26) -> 3.6073391 | K26: 0.03 | L26: =J26/((1+$C$5)^H26) -> 1.6387097 | N26: 10 | O26: 2034 | P26: =P25*(1+Q26) -> 2.3632268 | Q26: 0.03 | R26: =P26/((1+$C$5)^N26) -> 1.0735455
B29: PV opf 10y Dividends | C29: =SUM(F17:F26) -> 13.654632 | H29: PV opf 10y Dividends | I29: =SUM(L17:L26) -> 15.043218 | N29: PV opf 10y Dividends | O29: =SUM(R17:R26) -> 11.73375
B30: PV of Terminal Value | C30: =-PV(C5,10,0,(D26*(1+C8)/(C5-C8))) -> 27.708861 | H30: PV of Terminal Value | I30: =-PV(I5,10,0,(J26*(1+I8)/(I5-I8))) -> 32.395058 | N30: PV of Terminal Value | O30: =-PV(O5,10,0,(P26*(1+O8)/(O5-O8))) -> 21.222532
B31: Sum of Total | C31: =SUM(C29:C30) -> 41.363493 | H31: Sum of Total | I31: =SUM(I29:I30) -> 47.438276 | N31: Sum of Total | O31: =SUM(O29:O30) -> 32.956282
B33: Current Market Value | C33: 67.05 | H33: Current Market Value | I33: 67.05 | N33: Current Market Value | O33: 67.05
B34: Valuation Gap | C34: =(C31-C33)/C33 -> -0.38309481 | D34: SELL | H34: Valuation Gap | I34: =(I31-I33)/I33 -> -0.29249402 | J34: SELL | N34: Valuation Gap | O34: =(O31-O33)/O33 -> -0.50848201 | P34: SELL

Sheet FCFF
B2: BASE CASE | I2: BULL CASE | P2: BEAR CASE
B3: Assumptions: | I3: Assumptions: | P3: Assumptions:
B4: Tax Rate | C4: =-AVERAGE('EBAY Income Statement'!$B$25:$G$25) -> 0.22365735 | D4: Source: FactSet | I4: Tax Rate | J4: =-AVERAGE('EBAY Income Statement'!$B$25:$G$25) -> 0.22365735 | K4: Source: FactSet | P4: Tax Rate | Q4: =-AVERAGE('EBAY Income Statement'!$B$25:$G$25) -> 0.22365735 | R4: Source: FactSet
B5: Revenue growth | C5: 0.075 | D5: Source: Value Line | I5: Revenue growth | J5: 0.085 | K5: Source: Value Line | P5: Revenue growth | Q5: 0.065 | R5: Source: Value Line
B6: COGS as % Rev | C6: =(AVERAGE('EBAY Income Statement'!$B$6:$G$6)/AVERAGE('EBAY Income Statement'!$B$5:$G$5)) -> -0.25336799 | I6: COGS as % Rev | J6: -0.23 | P6: COGS as % Rev | Q6: =-0.27 -> -0.27
B7: Expenses as % of Rev | C7: =AVERAGE('EBAY Income Statement'!$B$8:$G$8)/AVERAGE('EBAY Income Statement'!$B$5:$G$5) -> -0.50181793 | I7: Expenses as % of Rev | J7: -0.47 | P7: Expenses as % of Rev | Q7: -0.52
B8: Dep & Amort | C8: =-'EBAY Income Statement'!$H$14 -> 0.0020164269 | I8: Dep & Amort | J8: =-'EBAY Income Statement'!$H$14 -> 0.0020164269 | P8: Dep & Amort | Q8: =-'EBAY Income Statement'!$H$14 -> 0.0020164269
B9: CAPEX as % of Rev | C9: ='EBAY Balance Sheet'!$H$21 -> 0.13875833 | I9: CAPEX as % of Rev | J9: ='EBAY Balance Sheet'!$H$21 -> 0.13875833 | P9: CAPEX as % of Rev | Q9: ='EBAY Balance Sheet'!$H$21 -> 0.13875833
B10: Required rate of return | C10: ='CAPM and WACC'!$B$7 -> 0.0769 | D10: Source: FactSet | I10: Required rate of return | J10: ='CAPM and WACC'!$B$7 -> 0.0769 | K10: Source: FactSet | P10: Required rate of return | Q10: ='CAPM and WACC'!$B$7 -> 0.0769 | R10: Source: FactSet
B11: Terminal Growth Rate | C11: 0.025 | I11: Terminal Growth Rate | J11: 0.027 | P11: Terminal Growth Rate | Q11: 0.023
B13: Year (index) | C13: 1 | D13: 1 | E13: 3 | F13: 4 | G13: 5 | I13: Year (index) | J13: 1 | K13: 1 | L13: 3 | M13: 4 | N13: 5 | P13: Year (index) | Q13: 1 | R13: 1 | S13: 3 | T13: 4 | U13: 5
B14: Year | C14: 2025 | D14: 2026 | E14: 2027 | F14: 2028 | G14: 2029 | I14: Year | J14: 2025 | K14: 2026 | L14: 2027 | M14: 2028 | N14: 2029 | P14: Year | Q14: 2025 | R14: 2026 | S14: 2027 | T14: 2028 | U14: 2029
B15: Sales | C15: ='EBAY Income Statement'!$G$5*(1+$C$5) -> 11054.225 | D15: =C15*(1+$C$5) -> 11883.292 | E15: =D15*(1+$C$5) -> 12774.539 | F15: =E15*(1+$C$5) -> 13732.629 | G15: =F15*(1+$C$5) -> 14762.576 | I15: Sales | J15: ='EBAY Income Statement'!$G$5*(1+$J$5) -> 11157.055 | K15: =J15*(1+$J$5) -> 12105.405 | L15: =K15*(1+$J$5) -> 13134.364 | M15: =L15*(1+$J$5) -> 14250.785 | N15: =M15*(1+$J$5) -> 15462.102 | P15: Sales | Q15: ='EBAY Income Statement'!$G$5*(1+$Q$5) -> 10951.395 | R15: =Q15*(1+$Q$5) -> 11663.236 | S15: =R15*(1+$Q$5) -> 12421.346 | T15: =S15*(1+$Q$5) -> 13228.733 | U15: =T15*(1+$Q$5) -> 14088.601
B16: COGS | C16: =C15*$C$6 -> -2800.7868 | D16: =D15*$C$6 -> -3010.8458 | E16: =E15*$C$6 -> -3236.6593 | F16: =F15*$C$6 -> -3479.4087 | G16: =G15*$C$6 -> -3740.3644 | I16: COGS | J16: =J15*$J$6 -> -2566.1227 | K16: =K15*$J$6 -> -2784.2431 | L16: =L15*$J$6 -> -3020.9037 | M16: =M15*$J$6 -> -3277.6806 | N16: =N15*$J$6 -> -3556.2834 | P16: COGS | Q16: =Q15*$Q$6 -> -2956.8766 | R16: =R15*$Q$6 -> -3149.0736 | S16: =S15*$Q$6 -> -3353.7634 | T16: =T15*$Q$6 -> -3571.758 | U16: =U15*$Q$6 -> -3803.9223
B17: Gross Profit | C17: =SUM(C15:C16) -> 8253.4382 | D17: =SUM(D15:D16) -> 8872.4461 | E17: =SUM(E15:E16) -> 9537.8795 | F17: =SUM(F15:F16) -> 10253.22 | G17: =SUM(G15:G16) -> 11022.212 | I17: Gross Profit | J17: =SUM(J15:J16) -> 8590.9323 | K17: =SUM(K15:K16) -> 9321.1616 | L17: =SUM(L15:L16) -> 10113.46 | M17: =SUM(M15:M16) -> 10973.104 | N17: =SUM(N15:N16) -> 11905.818 | P17: Gross Profit | Q17: =SUM(Q15:Q16) -> 7994.5183 | R17: =SUM(R15:R16) -> 8514.162 | S17: =SUM(S15:S16) -> 9067.5826 | T17: =SUM(T15:T16) -> 9656.9754 | U17: =SUM(U15:U16) -> 10284.679
B18: Expenses | C18: =C15*$C$7 -> -5547.2083 | D18: =D15*$C$7 -> -5963.2489 | E18: =E15*$C$7 -> -6410.4926 | F18: =F15*$C$7 -> -6891.2795 | G18: =G15*$C$7 -> -7408.1255 | I18: Expenses | J18: =J15*$J$7 -> -5243.8158 | K18: =K15*$J$7 -> -5689.5402 | L18: =L15*$J$7 -> -6173.1511 | M18: =M15*$J$7 -> -6697.869 | N18: =N15*$J$7 -> -7267.1878 | P18: Expenses | Q18: =Q15*$Q$7 -> -5694.7254 | R18: =R15*$Q$7 -> -6064.8826 | S18: =S15*$Q$7 -> -6459.0999 | T18: =T15*$Q$7 -> -6878.9414 | U18: =U15*$Q$7 -> -7326.0726
B19: EBIT | C19: =SUM(C17:C18) -> 2706.2299 | D19: =SUM(D17:D18) -> 2909.1972 | E19: =SUM(E17:E18) -> 3127.387 | F19: =SUM(F17:F18) -> 3361.941 | G19: =SUM(G17:G18) -> 3614.0865 | I19: EBIT | J19: =SUM(J17:J18) -> 3347.1165 | K19: =SUM(K17:K18) -> 3631.6214 | L19: =SUM(L17:L18) -> 3940.3092 | M19: =SUM(M17:M18) -> 4275.2355 | N19: =SUM(N17:N18) -> 4638.6305 | P19: EBIT | Q19: =SUM(Q17:Q18) -> 2299.7929 | R19: =SUM(R17:R18) -> 2449.2795 | S19: =SUM(S17:S18) -> 2608.4827 | T19: =SUM(T17:T18) -> 2778.034 | U19: =SUM(U17:U18) -> 2958.6062
B20: Tax Expense | C20: =-C19*$C$4 -> -605.26822 | D20: =-D19*$C$4 -> -650.66333 | E20: =-E19*$C$4 -> -699.46308 | F20: =-F19*$C$4 -> -751.92281 | G20: =-G19*$C$4 -> -808.31702 | I20: Tax Expense | J20: =-J19*$C$4 -> -748.60721 | K20: =-K19*$C$4 -> -812.23882 | L20: =-L19*$C$4 -> -881.27912 | M20: =-M19*$C$4 -> -956.18785 | N20: =-N19*$C$4 -> -1037.4638 | P20: Tax Expense | Q20: =-Q19*$C$4 -> -514.3656 | R20: =-R19*$C$4 -> -547.79936 | S20: =-S19*$C$4 -> -583.40632 | T20: =-T19*$C$4 -> -621.32773 | U20: =-U19*$C$4 -> -661.71404
B21: NOPAT | C21: =SUM(C19:C20) -> 2100.9617 | D21: =SUM(D19:D20) -> 2258.5338 | E21: =SUM(E19:E20) -> 2427.9239 | F21: =SUM(F19:F20) -> 2610.0182 | G21: =SUM(G19:G20) -> 2805.7695 | I21: NOPAT | J21: =SUM(J19:J20) -> 2598.5093 | K21: =SUM(K19:K20) -> 2819.3826 | L21: =SUM(L19:L20) -> 3059.0301 | M21: =SUM(M19:M20) -> 3319.0477 | N21: =SUM(N19:N20) -> 3601.1667 | P21: NOPAT | Q21: =SUM(Q19:Q20) -> 1785.4274 | R21: =SUM(R19:R20) -> 1901.4801 | S21: =SUM(S19:S20) -> 2025.0763 | T21: =SUM(T19:T20) -> 2156.7063 | U21: =SUM(U19:U20) -> 2296.8922
B22: Dep and Amort | C22: =$C$8*C15 -> 22.290036 | D22: =$C$8*D15 -> 23.961789 | E22: =$C$8*E15 -> 25.758923 | F22: =$C$8*F15 -> 27.690842 | G22: =$C$8*G15 -> 29.767656 | I22: Dep and Amort | J22: =$J$8*J15 -> 22.497385 | K22: =$J$8*K15 -> 24.409663 | L22: =$J$8*L15 -> 26.484485 | M22: =$J$8*M15 -> 28.735666 | N22: =$J$8*N15 -> 31.178197 | P22: Dep and Amort | Q22: =$Q$8*Q15 -> 22.082687 | R22: =$Q$8*R15 -> 23.518062 | S22: =$Q$8*S15 -> 25.046736 | T22: =$Q$8*T15 -> 26.674774 | U22: =$Q$8*U15 -> 28.408634
B23: Change in NWC | C23: -301.37 | D23: {=-'EBAY Balance Sheet'!$R$5:$U$5} -> -346.03867 | E23: -371.99157 | F23: -399.89094 | G23: -429.88276 | I23: Change in NWC | J23: -301.37 | K23: {=-'EBAY Balance Sheet'!$R$5:$U$5} -> -346.03867 | L23: -371.99157 | M23: -399.89094 | N23: -429.88276 | P23: Change in NWC | Q23: -301.37 | R23: {=-'EBAY Balance Sheet'!$R$5:$U$5} -> -346.03867 | S23: -371.99157 | T23: -399.89094 | U23: -429.88276
B24: Captial Expendatures | C24: {=-'EBAY Balance Sheet'!$H$20:$L$20} -> -270.86582 | D24: -115.03994 | E24: -123.66793 | F24: -132.94303 | G24: -142.91375 | I24: Captial Expendatures | J24: {=-'EBAY Balance Sheet'!$H$23:$L$23} -> -285.13434 | K24: -131.59142 | L24: -142.77669 | M24: -154.91271 | N24: -168.08029 | P24: Captial Expendatures | Q24: {=-'EBAY Balance Sheet'!$H$26:$L$26} -> -256.5973 | R24: -98.773825 | S24: -105.19412 | T24: -112.03174 | U24: -119.3138
B25: FCFF | C25: =SUM(C21:C24) -> 1551.0159 | D25: =SUM(D21:D24) -> 1821.417 | E25: =SUM(E21:E24) -> 1958.0233 | F25: =SUM(F21:F24) -> 2104.875 | G25: =SUM(G21:G24) -> 2262.7407 | I25: FCFF | J25: =SUM(J21:J24) -> 2034.5023 | K25: =SUM(K21:K24) -> 2366.1621 | L25: =SUM(L21:L24) -> 2570.7463 | M25: =SUM(M21:M24) -> 2792.9797 | N25: =SUM(N21:N24) -> 3034.3819 | P25: FCFF | Q25: =SUM(Q21:Q24) -> 1249.5427 | R25: =SUM(R21:R24) -> 1480.1857 | S25: =SUM(S21:S24) -> 1572.9374 | T25: =SUM(T21:T24) -> 1671.4584 | U25: =SUM(U21:U24) -> 1776.1043
B26: Present Value | C26: =C25/(1+$C$10)^C13 -> 1440.2599 | D26: =D25/(1+$C$10)^D13 -> 1691.352 | E26: =E25/(1+$C$10)^E13 -> 1567.8038 | F26: =F25/(1+$C$10)^F13 -> 1565.0377 | G26: =G25/(1+$C$10)^G13 -> 1562.2765 | I26: Present Value | J26: =J25/(1+$C$10)^J13 -> 1889.2212 | K26: =K25/(1+$C$10)^K13 -> 2197.1977 | L26: =L25/(1+$C$10)^L13 -> 2058.4157 | M26: =M25/(1+$C$10)^M13 -> 2076.6642 | N26: =N25/(1+$C$10)^N13 -> 2095.045 | P26: Present Value | Q26: =Q25/(1+$C$10)^Q13 -> 1160.3145 | R26: =R25/(1+$C$10)^R13 -> 1374.4876 | S26: =S25/(1+$C$10)^S13 -> 1259.4627 | T26: =T25/(1+$C$10)^T13 -> 1242.7794 | U26: =U25/(1+$C$10)^U13 -> 1226.2854
B28: Sum of PV of FCFF | C28: =SUM(C26:G26) -> 7826.73 | I28: Sum of PV of FCFF | J28: =SUM(J26:N26) -> 10316.544 | P28: Sum of PV of FCFF | Q28: =SUM(Q26:U26) -> 6263.3297
B29: PV of terminal Value | C29: =-PV(C10,5,0,(G25*(1+C11))/(C10-C11)) -> 30854.208 | I29: PV of terminal Value | J29: =-PV(J10,5,0,(N25*(1+J11))/(J10-J11)) -> 43118.46 | P29: PV of terminal Value | Q29: =-PV(Q10,5,0,(U25*(1+Q11))/(Q10-Q11)) -> 23274.397
B30: Enterprise Value | C30: =SUM(C28:C29) -> 38680.938 | I30: Enterprise Value | J30: =SUM(J28:J29) -> 53435.004 | P30: Enterprise Value | Q30: =SUM(Q28:Q29) -> 29537.727
B32: + Cash | C32: ='EBAY Balance Sheet'!$G$9 -> 2433 | I32: + Cash | J32: ='EBAY Balance Sheet'!$G$9 -> 2433 | P32: + Cash | Q32: ='EBAY Balance Sheet'!$G$9 -> 2433
B33: - Debt | C33: =-('EBAY Balance Sheet'!$G$43+'EBAY Balance Sheet'!$G$56) -> -7425 | I33: - Debt | J33: =-('EBAY Balance Sheet'!$G$43+'EBAY Balance Sheet'!$G$56) -> -7425 | P33: - Debt | Q33: =-('EBAY Balance Sheet'!$G$43+'EBAY Balance Sheet'!$G$56) -> -7425
B34: Implied Equity Value | C34: =SUM(C30:C33) -> 33688.938 | I34: Implied Equity Value | J34: =SUM(J30:J33) -> 48443.004 | P34: Implied Equity Value | Q34: =SUM(Q30:Q33) -> 24545.727
B36: Shares outstanding | C36: 479 | I36: Shares outstanding | J36: 479 | P36: Shares outstanding | Q36: 479
B37: Equity Per Share | C37: =C34/C36 -> 70.331812 | I37: Equity Per Share | J37: =J34/J36 -> 101.13362 | P37: Equity Per Share | Q37: =Q34/Q36 -> 51.243689
B39: Current Market Value | C39: 67.05 | I39: Current Market Value | J39: 67.05 | P39: Current Market Value | Q39: 67.05
B40: Valuation Gap | C40: =(C37-C39)/C39 -> 0.048945746 | D40: BUY | I40: Valuation Gap | J40: =(J37-J39)/J39 -> 0.5083314 | K40: BUY | P40: Valuation Gap | Q40: =(Q37-Q39)/Q39 -> -0.23573917 | R40: SELL

Sheet FCFE
B2: BASE CASE | I2: BULL CASE | P2: BEAR CASE
B3: Assumptions: | I3: Assumptions: | P3: Assumptions:
B4: Tax Rate | C4: =-AVERAGE('EBAY Income Statement'!$B$25:$G$25) -> 0.22365735 | D4: Source: FactSet | I4: Tax Rate | J4: =-AVERAGE('EBAY Income Statement'!$B$25:$G$25) -> 0.22365735 | K4: Source: FactSet | P4: Tax Rate | Q4: =-AVERAGE('EBAY Income Statement'!$B$25:$G$25) -> 0.22365735 | R4: Source: FactSet
B5: Revenue growth | C5: 0.075 | D5: Source: Value Line | I5: Revenue growth | J5: 0.085 | K5: Source: Value Line | P5: Revenue growth | Q5: 0.065 | R5: Source: Value Line
B6: COGS as % sales | C6: =(AVERAGE('EBAY Income Statement'!$B$6:$G$6)/AVERAGE('EBAY Income Statement'!$B$5:$G$5)) -> -0.25336799 | I6: COGS as % sales | J6: -0.22 | P6: COGS as % sales | Q6: -0.27
B7: Expenses as % of sales | C7: =(AVERAGE('EBAY Income Statement'!$B$8:$G$8)/AVERAGE('EBAY Income Statement'!$B$5:$G$5)) -> -0.50181793 | I7: Expenses as % of sales | J7: -0.47 | P7: Expenses as % of sales | Q7: -0.52
B8: Interest Expense as % | C8: ='EBAY Income Statement'!$H$19 -> -0.01708644 | I8: Interest Expense as % | J8: ='EBAY Income Statement'!$H$19 -> -0.01708644 | P8: Interest Expense as % | Q8: ='EBAY Income Statement'!$H$19 -> -0.01708644
B9: Dep & Amort | C9: =-'EBAY Income Statement'!$H$14 -> 0.0020164269 | I9: Dep & Amort | J9: =-'EBAY Income Statement'!$H$14 -> 0.0020164269 | P9: Dep & Amort | Q9: =-'EBAY Income Statement'!$H$14 -> 0.0020164269
B10: CAPEX as % of Rev | C10: ='EBAY Balance Sheet'!$H$21 -> 0.13875833 | I10: CAPEX as % of Rev | J10: ='EBAY Balance Sheet'!$H$21 -> 0.13875833 | P10: CAPEX as % of Rev | Q10: ='EBAY Balance Sheet'!$H$21 -> 0.13875833
B11: Debt Issuance % | C11: ='EBAY Cash Flows'!$H$56 -> 0.092158747 | I11: Debt Issuance % | J11: 0.11 | P11: Debt Issuance % | Q11: ='EBAY Cash Flows'!$H$56 -> 0.092158747
B12: Debt Repayment % | C12: ='EBAY Cash Flows'!$H$58 -> -0.14061723 | I12: Debt Repayment % | J12: ='EBAY Cash Flows'!$H$58 -> -0.14061723 | P12: Debt Repayment % | Q12: -0.16
B13: Required Rate of Return | C13: ='CAPM and WACC'!$B$5 -> 0.082102733 | I13: Required Rate of Return | J13: ='CAPM and WACC'!$B$5 -> 0.082102733 | P13: Required Rate of Return | Q13: ='CAPM and WACC'!$B$5 -> 0.082102733
B14: Terminal Growth Rate | C14: 0.025 | I14: Terminal Growth Rate | J14: 0.027 | P14: Terminal Growth Rate | Q14: 0.023
B16: Year (index) | C16: 1 | D16: 2 | E16: 3 | F16: 4 | G16: 5 | I16: Year (index) | J16: 1 | K16: 2 | L16: 3 | M16: 4 | N16: 5 | P16: Year (index) | Q16: 1 | R16: 2 | S16: 3 | T16: 4 | U16: 5
B17: Year | C17: 2025 | D17: 2026 | E17: 2027 | F17: 2028 | G17: 2029 | I17: Year | J17: 2025 | K17: 2026 | L17: 2027 | M17: 2028 | N17: 2029 | P17: Year | Q17: 2025 | R17: 2026 | S17: 2027 | T17: 2028 | U17: 2029
B18: Revenue | C18: ='EBAY Income Statement'!$G$5*(1+$C$5) -> 11054.225 | D18: =C18*(1+$C$5) -> 11883.292 | E18: =D18*(1+$C$5) -> 12774.539 | F18: =E18*(1+$C$5) -> 13732.629 | G18: =F18*(1+$C$5) -> 14762.576 | I18: Revenue | J18: ='EBAY Income Statement'!$G$5*(1+$J$5) -> 11157.055 | K18: =J18*(1+$J$5) -> 12105.405 | L18: =K18*(1+$J$5) -> 13134.364 | M18: =L18*(1+$J$5) -> 14250.785 | N18: =M18*(1+$J$5) -> 15462.102 | P18: Revenue | Q18: ='EBAY Income Statement'!$G$5*(1+$Q$5) -> 10951.395 | R18: =Q18*(1+$Q$5) -> 11663.236 | S18: =R18*(1+$Q$5) -> 12421.346 | T18: =S18*(1+$Q$5) -> 13228.733 | U18: =T18*(1+$Q$5) -> 14088.601
B19: Cogs | C19: =C18*$C$6 -> -2800.7868 | D19: =D18*$C$6 -> -3010.8458 | E19: =E18*$C$6 -> -3236.6593 | F19: =F18*$C$6 -> -3479.4087 | G19: =G18*$C$6 -> -3740.3644 | I19: Cogs | J19: =J18*$J$6 -> -2454.5521 | K19: =K18*$J$6 -> -2663.189 | L19: =L18*$J$6 -> -2889.5601 | M19: =M18*$J$6 -> -3135.1727 | N19: =N18*$J$6 -> -3401.6624 | P19: Cogs | Q19: =Q18*$Q$6 -> -2956.8766 | R19: =R18*$Q$6 -> -3149.0736 | S19: =S18*$Q$6 -> -3353.7634 | T19: =T18*$Q$6 -> -3571.758 | U19: =U18*$Q$6 -> -3803.9223
B20: Gross Profit | C20: =SUM(C18:C19) -> 8253.4382 | D20: =SUM(D18:D19) -> 8872.4461 | E20: =SUM(E18:E19) -> 9537.8795 | F20: =SUM(F18:F19) -> 10253.22 | G20: =SUM(G18:G19) -> 11022.212 | I20: Gross Profit | J20: =SUM(J18:J19) -> 8702.5029 | K20: =SUM(K18:K19) -> 9442.2156 | L20: =SUM(L18:L19) -> 10244.804 | M20: =SUM(M18:M19) -> 11115.612 | N20: =SUM(N18:N19) -> 12060.439 | P20: Gross Profit | Q20: =SUM(Q18:Q19) -> 7994.5183 | R20: =SUM(R18:R19) -> 8514.162 | S20: =SUM(S18:S19) -> 9067.5826 | T20: =SUM(T18:T19) -> 9656.9754 | U20: =SUM(U18:U19) -> 10284.679
B21: Expenses | C21: =C18*$C$7 -> -5547.2083 | D21: =D18*$C$7 -> -5963.2489 | E21: =E18*$C$7 -> -6410.4926 | F21: =F18*$C$7 -> -6891.2795 | G21: =G18*$C$7 -> -7408.1255 | I21: Expenses | J21: =J18*$J$7 -> -5243.8158 | K21: =K18*$J$7 -> -5689.5402 | L21: =L18*$J$7 -> -6173.1511 | M21: =M18*$J$7 -> -6697.869 | N21: =N18*$J$7 -> -7267.1878 | P21: Expenses | Q21: =Q18*$Q$7 -> -5694.7254 | R21: =R18*$Q$7 -> -6064.8826 | S21: =S18*$Q$7 -> -6459.0999 | T21: =T18*$Q$7 -> -6878.9414 | U21: =U18*$Q$7 -> -7326.0726
B22: EBIT | C22: =SUM(C20:C21) -> 2706.2299 | D22: =SUM(D20:D21) -> 2909.1972 | E22: =SUM(E20:E21) -> 3127.387 | F22: =SUM(F20:F21) -> 3361.941 | G22: =SUM(G20:G21) -> 3614.0865 | I22: EBIT | J22: =SUM(J20:J21) -> 3458.687 | K22: =SUM(K20:K21) -> 3752.6754 | L22: =SUM(L20:L21) -> 4071.6529 | M22: =SUM(M20:M21) -> 4417.7434 | N22: =SUM(N20:N21) -> 4793.2515 | P22: EBIT | Q22: =SUM(Q20:Q21) -> 2299.7929 | R22: =SUM(R20:R21) -> 2449.2795 | S22: =SUM(S20:S21) -> 2608.4827 | T22: =SUM(T20:T21) -> 2778.034 | U22: =SUM(U20:U21) -> 2958.6062
B23: Tax Expense | C23: =-C22*($C$4) -> -605.26822 | D23: =-D22*($C$4) -> -650.66333 | E23: =-E22*($C$4) -> -699.46308 | F23: =-F22*($C$4) -> -751.92281 | G23: =-G22*($C$4) -> -808.31702 | I23: Tax Expense | J23: =-J22*($C$4) -> -773.56078 | K23: =-K22*($C$4) -> -839.31345 | L23: =-L22*($C$4) -> -910.65509 | M23: =-M22*($C$4) -> -988.06078 | N23: =-N22*($C$4) -> -1072.0459 | P23: Tax Expense | Q23: =-Q22*($C$4) -> -514.3656 | R23: =-R22*($C$4) -> -547.79936 | S23: =-S22*($C$4) -> -583.40632 | T23: =-T22*($C$4) -> -621.32773 | U23: =-U22*($C$4) -> -661.71404
B24: Interest Expense | C24: =$C$8*C18 -> -188.87735 | D24: =$C$8*D18 -> -203.04315 | E24: =$C$8*E18 -> -218.27138 | F24: =$C$8*F18 -> -234.64174 | G24: =$C$8*G18 -> -252.23987 | I24: Interest Expense | J24: =$J$8*J18 -> -190.63435 | K24: =$J$8*K18 -> -206.83826 | L24: =$J$8*L18 -> -224.41952 | M24: =$J$8*M18 -> -243.49518 | N24: =$J$8*N18 -> -264.19227 | P24: Interest Expense | Q24: =$Q$8*Q18 -> -187.12035 | R24: =$Q$8*R18 -> -199.28317 | S24: =$Q$8*S18 -> -212.23658 | T24: =$Q$8*T18 -> -226.03195 | U24: =$Q$8*U18 -> -240.72403
B25: Net Income | C25: =SUM(C22:C24) -> 1912.0844 | D25: =SUM(D22:D24) -> 2055.4907 | E25: =SUM(E22:E24) -> 2209.6525 | F25: =SUM(F22:F24) -> 2375.3764 | G25: =SUM(G22:G24) -> 2553.5297 | I25: Net Income | J25: =SUM(J22:J24) -> 2494.4919 | K25: =SUM(K22:K24) -> 2706.5237 | L25: =SUM(L22:L24) -> 2936.5783 | M25: =SUM(M22:M24) -> 3186.1874 | N25: =SUM(N22:N24) -> 3457.0133 | P25: Net Income | Q25: =SUM(Q22:Q24) -> 1598.307 | R25: =SUM(R22:R24) -> 1702.197 | S25: =SUM(S22:S24) -> 1812.8398 | T25: =SUM(T22:T24) -> 1930.6743 | U25: =SUM(U22:U24) -> 2056.1682
B26: Dep and Amort | C26: =$C$9*C18 -> 22.290036 | D26: =$C$9*D18 -> 23.961789 | E26: =$C$9*E18 -> 25.758923 | F26: =$C$9*F18 -> 27.690842 | G26: =$C$9*G18 -> 29.767656 | I26: Dep and Amort | J26: =$C$9*J18 -> 22.497385 | K26: =$C$9*K18 -> 24.409663 | L26: =$C$9*L18 -> 26.484485 | M26: =$C$9*M18 -> 28.735666 | N26: =$C$9*N18 -> 31.178197 | P26: Dep and Amort | Q26: =$Q$9*Q18 -> 22.082687 | R26: =$Q$9*R18 -> 23.518062 | S26: =$Q$9*S18 -> 25.046736 | T26: =$Q$9*T18 -> 26.674774 | U26: =$Q$9*U18 -> 28.408634
B27: Change in NWC | C27: -301.37 | D27: {=-'EBAY Balance Sheet'!$R$5:$U$5} -> -346.03867 | E27: -371.99157 | F27: -399.89094 | G27: -429.88276 | I27: Change in NWC | J27: -301.37 | K27: {=-'EBAY Balance Sheet'!$R$5:$U$5} -> -346.03867 | L27: -371.99157 | M27: -399.89094 | N27: -429.88276 | P27: Change in NWC | Q27: -301.37 | R27: {=-'EBAY Balance Sheet'!$R$5:$U$5} -> -346.03867 | S27: -371.99157 | T27: -399.89094 | U27: -429.88276
B28: Captial Expendatures | C28: {=-'EBAY Balance Sheet'!H20:L20} -> -270.86582 | D28: -115.03994 | E28: -123.66793 | F28: -132.94303 | G28: -142.91375 | I28: Captial Expendatures | J28: {=-'EBAY Balance Sheet'!H23:L23} -> -285.13434 | K28: -131.59142 | L28: -142.77669 | M28: -154.91271 | N28: -168.08029 | P28: Captial Expendatures | Q28: {=-'EBAY Balance Sheet'!H26:L26} -> -256.5973 | R28: -98.773825 | S28: -105.19412 | T28: -112.03174 | U28: -119.3138
B29: Long term debt issuance | C29: =$C$11*C18 -> 1018.7435 | D29: =$C$11*D18 -> 1095.1493 | E29: =$C$11*E18 -> 1177.2855 | F29: =$C$11*F18 -> 1265.5819 | G29: =$C$11*G18 -> 1360.5005 | I29: Long term debt issuance | J29: =$J$11*J18 -> 1227.276 | K29: =$J$11*K18 -> 1331.5945 | L29: =$J$11*L18 -> 1444.78 | M29: =$J$11*M18 -> 1567.5864 | N29: =$J$11*N18 -> 1700.8312 | P29: Long term debt issuance | Q29: =$Q$11*Q18 -> 1009.2668 | R29: =$Q$11*R18 -> 1074.8692 | S29: =$Q$11*S18 -> 1144.7357 | T29: =$Q$11*T18 -> 1219.1435 | U29: =$Q$11*U18 -> 1298.3878
B30: Long term debt repayments | C30: =$C$12*C18 -> -1554.4145 | D30: =$C$12*D18 -> -1670.9956 | E30: =$C$12*E18 -> -1796.3203 | F30: =$C$12*F18 -> -1931.0443 | G30: =$C$12*G18 -> -2075.8726 | I30: Long term debt repayments | J30: =$C$12*J18 -> -1568.8742 | K30: =$C$12*K18 -> -1702.2285 | L30: =$C$12*L18 -> -1846.9179 | M30: =$C$12*M18 -> -2003.9059 | N30: =$C$12*N18 -> -2174.2379 | P30: Long term debt repayments | Q30: =$Q$12*Q18 -> -1752.2232 | R30: =$Q$12*R18 -> -1866.1177 | S30: =$Q$12*S18 -> -1987.4154 | T30: =$Q$12*T18 -> -2116.5974 | U30: =$Q$12*U18 -> -2254.1762
B31: FCFE | C31: =SUM(C25:C30) -> 826.4676 | D31: =SUM(D25:D30) -> 1042.5276 | E31: =SUM(E25:E30) -> 1120.7171 | F31: =SUM(F25:F30) -> 1204.7709 | G31: =SUM(G25:G30) -> 1295.1287 | I31: FCFE | J31: =SUM(J25:J30) -> 1588.8869 | K31: =SUM(K25:K30) -> 1882.6693 | L31: =SUM(L25:L30) -> 2046.1566 | M31: =SUM(M25:M30) -> 2223.7999 | N31: =SUM(N25:N30) -> 2416.8218 | P31: FCFE | Q31: =SUM(Q25:Q30) -> 319.46603 | R31: =SUM(R25:R30) -> 489.654 | S31: =SUM(S25:S30) -> 518.02112 | T31: =SUM(T25:T30) -> 547.97258 | U31: =SUM(U25:U30) -> 579.59189
B32: Present Value | C32: =-PV($C$13,C16,0,C31) -> 763.76076 | D32: =-PV($C$13,D16,0,D31) -> 890.32909 | E32: =-PV($C$13,E16,0,E31) -> 884.48512 | F32: =-PV($C$13,F16,0,F31) -> 878.67952 | G32: =-PV($C$13,G16,0,G31) -> 872.91202 | I32: Present Value | J32: =-PV($C$13,J16,0,J31) -> 1468.3327 | K32: =-PV($C$13,K16,0,K31) -> 1607.8187 | L32: =-PV($C$13,L16,0,L31) -> 1614.8545 | M32: =-PV($C$13,M16,0,M31) -> 1621.8912 | N32: =-PV($C$13,N16,0,N31) -> 1628.929 | P32: Present Value | Q32: =-PV($C$13,Q16,0,Q31) -> 295.22708 | R32: =-PV($C$13,R16,0,R31) -> 418.16947 | S32: =-PV($C$13,S16,0,S31) -> 408.82928 | T32: =-PV($C$13,T16,0,T31) -> 399.65463 | U32: =-PV($C$13,U16,0,U31) -> 390.64281
B34: Sum of PV of FCFE | C34: =SUM(C32:G32) -> 4290.1665 | I34: Sum of PV of FCFE | J34: =SUM(J32:N32) -> 7941.8261 | P34: Sum of PV of FCFE | Q34: =SUM(Q32:U32) -> 1912.5233
B35: Terminal Value of FCFE | C35: =-PV(C13,6,0,G31/(C13-C14)) -> 14126.842 | I35: Terminal Value of FCFE | J35: =-PV(J13,6,0,N31/(J13-J14)) -> 27318.731 | P35: Terminal Value of FCFE | Q35: =-PV(Q13,6,0,U31/(Q13-Q14)) -> 6108.0668
B36: Equity Value | C36: =SUM(C34:C35) -> 18417.009 | I36: Equity Value | J36: =SUM(J34:J35) -> 35260.557 | P36: Equity Value | Q36: =SUM(Q34:Q35) -> 8020.59
B38: Shares Outstanding (M) | C38: 479 | I38: Shares Outstanding (M) | J38: 479 | P38: Shares Outstanding (M) | Q38: 479
B39: Equity Per Share | C39: =C36/C38 -> 38.44887 | I39: Equity Per Share | J39: =J36/J38 -> 73.612854 | P39: Equity Per Share | Q39: =Q36/Q38 -> 16.744447
B41: Current Market Value | C41: 67.05 | I41: Current Market Value | J41: 67.05 | P41: Current Market Value | Q41: 67.05
B42: Valuation Gap | C42: =(C39-C41)/C41 -> -0.42656421 | D42: SELL | I42: Valuation Gap | J42: =(J39-J41)/J41 -> 0.097880005 | K42: BUY | P42: Valuation Gap | Q42: =(Q39-Q41)/Q41 -> -0.75026925 | R42: SELL

Sheet CI - Stock PX
A1: Security | B1: CI US Equity | C1: KEY | D1: calculated row | E1: Non useful
A2: Start Date | B2: 43553
A3: End Date | B3: 45747
A4: Period | B4: M
A5: Currency | B5: USD
A7: Date | B7: Lookup Date | C7: PX_LAST | D7: Dividends paid | E7: PX_Change | F7: Risk Free (10yrbd) | G7: Return
A8: 45747 | B8: =_xlfn.CONCAT(MONTH(A8),"-",YEAR(A8)) -> 3-2025 | C8: 329.18 | D8: =IFERROR(INDEX('CI - dividend'!H:H,MATCH(B8,'CI - dividend'!D:D,0)),0) -> 1.51 | E8: =((C8+D8)-(C9+D9))/(C8+D8) -> 0.066588043 | F8: =INDEX('10YR Treasury'!E:E,MATCH(B8,'10YR Treasury'!B:B,0)) -> 0.0035044167 | G8: =E8-F8 -> 0.063083627
A9: 45716 | B9: =_xlfn.CONCAT(MONTH(A9),"-",YEAR(A9)) -> 2-2025 | C9: 308.67 | D9: =IFERROR(INDEX('CI - dividend'!H:H,MATCH(B9,'CI - dividend'!D:D,0)),0) -> 0 | E9: =((C9+D9)-(C10+D10))/(C9+D9) -> 0.046878543 | F9: =INDEX('10YR Treasury'!E:E,MATCH(B9,'10YR Treasury'!B:B,0)) -> 0.0035068333 | G9: =E9-F9 -> 0.04337171
A10: 45688 | B10: =_xlfn.CONCAT(MONTH(A10),"-",YEAR(A10)) -> 1-2025 | C10: 294.2 | D10: =IFERROR(INDEX('CI - dividend'!H:H,MATCH(B10,'CI - dividend'!D:D,0)),0) -> 0 | E10: =((C10+D10)-(C11+D11))/(C10+D10) -> 0.056152277 | F10: =INDEX('10YR Treasury'!E:E,MATCH(B10,'10YR Treasury'!B:B,0)) -> 0.00378225 | G10: =E10-F10 -> 0.052370027
A11: 45657 | B11: =_xlfn.CONCAT(MONTH(A11),"-",YEAR(A11)) -> 12-2024 | C11: 276.28 | D11: =IFERROR(INDEX('CI - dividend'!H:H,MATCH(B11,'CI - dividend'!D:D,0)),0) -> 1.4 | E11: =((C11+D11)-(C12+D12))/(C11+D11) -> -0.21654422 | F11: =INDEX('10YR Treasury'!E:E,MATCH(B11,'10YR Treasury'!B:B,0)) -> 0.0038075 | G11: =E11-F11 -> -0.22035172
A12: 45625 | B12: =_xlfn.CONCAT(MONTH(A12),"-",YEAR(A12)) -> 11-2024 | C12: 337.81 | D12: =IFERROR(INDEX('CI - dividend'!H:H,MATCH(B12,'CI - dividend'!D:D,0)),0) -> 0 | E12: =((C12+D12)-(C13+D13))/(C12+D12) -> 0.068766466 | F12: =INDEX('10YR Treasury'!E:E,MATCH(B12,'10YR Treasury'!B:B,0)) -> 0.00347375 | G12: =E12-F12 -> 0.065292716
A13: 45596 | B13: =_xlfn.CONCAT(MONTH(A13),"-",YEAR(A13)) -> 10-2024 | C13: 314.58 | D13: =IFERROR(INDEX('CI - dividend'!H:H,MATCH(B13,'CI - dividend'!D:D,0)),0) -> 0 | E13: =((C13+D13)-(C14+D14))/(C13+D13) -> -0.10569648 | F13: =INDEX('10YR Treasury'!E:E,MATCH(B13,'10YR Treasury'!B:B,0)) -> 0.0035703333 | G13: =E13-F13 -> -0.10926682
A14: 45565 | B14: =_xlfn.CONCAT(MONTH(A14),"-",YEAR(A14)) -> 9-2024 | C14: 346.43 | D14: =IFERROR(INDEX('CI - dividend'!H:H,MATCH(B14,'CI - dividend'!D:D,0)),0) -> 1.4 | E14: =((C14+D14)-(C15+D15))/(C14+D14) -> -0.039732053 | F14: =INDEX('10YR Treasury'!E:E,MATCH(B14,'10YR Treasury'!B:B,0)) -> 0.00315075 | G14: =E14-F14 -> -0.042882803
A15: 45534 | B15: =_xlfn.CONCAT(MONTH(A15),"-",YEAR(A15)) -> 8-2024 | C15: 361.65 | D15: =IFERROR(INDEX('CI - dividend'!H:H,MATCH(B15,'CI - dividend'!D:D,0)),0) -> 0 | E15: =((C15+D15)-(C16+D16))/(C15+D15) -> 0.0357528 | F15: =INDEX('10YR Treasury'!E:E,MATCH(B15,'10YR Treasury'!B:B,0)) -> 0.0032528333 | G15: =E15-F15 -> 0.032499966
A16: 45504 | B16: =_xlfn.CONCAT(MONTH(A16),"-",YEAR(A16)) -> 7-2024 | C16: 348.72 | D16: =IFERROR(INDEX('CI - dividend'!H:H,MATCH(B16,'CI - dividend'!D:D,0)),0) -> 0 | E16: =((C16+D16)-(C17+D17))/(C16+D16) -> 0.049151181 | F16: =INDEX('10YR Treasury'!E:E,MATCH(B16,'10YR Treasury'!B:B,0)) -> 0.003358 | G16: =E16-F16 -> 0.045793181
A17: 45471 | B17: =_xlfn.CONCAT(MONTH(A17),"-",YEAR(A17)) -> 6-2024 | C17: 330.18 | D17: =IFERROR(INDEX('CI - dividend'!H:H,MATCH(B17,'CI - dividend'!D:D,0)),0) -> 1.4 | E17: =((C17+D17)-(C18+D18))/(C17+D17) -> -0.038301466 | F17: =INDEX('10YR Treasury'!E:E,MATCH(B17,'10YR Treasury'!B:B,0)) -> 0.0036634167 | G17: =E17-F17 -> -0.041964882
A18: 45443 | B18: =_xlfn.CONCAT(MONTH(A18),"-",YEAR(A18)) -> 5-2024 | C18: 344.28 | D18: =IFERROR(INDEX('CI - dividend'!H:H,MATCH(B18,'CI - dividend'!D:D,0)),0) -> 0 | E18: =((C18+D18)-(C19+D19))/(C18+D18) -> -0.037469502 | F18: =INDEX('10YR Treasury'!E:E,MATCH(B18,'10YR Treasury'!B:B,0)) -> 0.00374875 | G18: =E18-F18 -> -0.041218252
A19: 45412 | B19: =_xlfn.CONCAT(MONTH(A19),"-",YEAR(A19)) -> 4-2024 | C19: 357.18 | D19: =IFERROR(INDEX('CI - dividend'!H:H,MATCH(B19,'CI - dividend'!D:D,0)),0) -> 0 | E19: =((C19+D19)-(C20+D20))/(C19+D19) -> -0.020745842 | F19: =INDEX('10YR Treasury'!E:E,MATCH(B19,'10YR Treasury'!B:B,0)) -> 0.0038998333 | G19: =E19-F19 -> -0.024645676
... A67: 43951 | B67: =_xlfn.CONCAT(MONTH(A67),"-",YEAR(A67)) -> 4-2020 | C67: 195.98 | D67: =IFERROR(INDEX('CI - dividend'!H:H,MATCH(B67,'CI - dividend'!D:D,0)),0) -> 0 | E67: =((C67+D67)-(C68+D68))/(C67+D67) -> 0.097663027 | F67: =INDEX('10YR Treasury'!E:E,MATCH(B67,'10YR Treasury'!B:B,0)) -> 0.00053275 | G67: =E67-F67 -> 0.097130277
A68: 43921 | B68: =_xlfn.CONCAT(MONTH(A68),"-",YEAR(A68)) -> 3-2020 | C68: 176.8 | D68: =IFERROR(INDEX('CI - dividend'!H:H,MATCH(B68,'CI - dividend'!D:D,0)),0) -> 0.04 | F68: =INDEX('10YR Treasury'!E:E,MATCH(B68,'10YR Treasury'!B:B,0)) -> 0.00055791667
B69: AVG | C69: =AVERAGE(C9:C68) -> 264.18267 | E69: =AVERAGE(E9:E68) -> 0.0061939937 | F69: =AVERAGE(F9:F68) -> 0.0023264222 | G69: =AVERAGE(G9:G68) -> 0.0038375968
B70: SD | C70: =STDEV(C9:C68) -> 55.504376 | E70: =STDEV(E9:E68) -> 0.080452342 | F70: =STDEV(F9:F68) -> 0.0011952435 | G70: =STDEV(G9:G68) -> 0.080513731
B71: total | C71: =(C8-C68)/C68 -> 0.86187783 | E71: geometric average

Sheet CI - dividend
B1: Declarati…↓ | C1: Ex Date | D1: Lookup Date | E1: Record | F1: Payable | G1: Curr | H1: Amount | I1: Type | J1: quarter end price
A2: 12) | B2: 45687 | C2: 45721 | D2: =_xlfn.CONCAT(MONTH(C2),"-",YEAR(C2)) -> 3-2025 | E2: 45721 | F2: 45736 | G2: USD | H2: 1.51 | I2: Regular Cash | J2: =INDEX('CI - Stock PX'!C:C,MATCH(D2,'CI - Stock PX'!B:B,0)) -> 329.18
A3: 13) | B3: 45588 | C3: 45630 | D3: =_xlfn.CONCAT(MONTH(C3),"-",YEAR(C3)) -> 12-2024 | E3: 45630 | F3: 45645 | G3: USD | H3: 1.4 | I3: Regular Cash | J3: =INDEX('CI - Stock PX'!C:C,MATCH(D3,'CI - Stock PX'!B:B,0)) -> 276.28
A4: 14) | B4: 45497 | C4: 45539 | D4: =_xlfn.CONCAT(MONTH(C4),"-",YEAR(C4)) -> 9-2024 | E4: 45539 | F4: 45554 | G4: USD | H4: 1.4 | I4: Regular Cash | J4: =INDEX('CI - Stock PX'!C:C,MATCH(D4,'CI - Stock PX'!B:B,0)) -> 346.43
A5: 15) | B5: 45406 | C5: 45447 | D5: =_xlfn.CONCAT(MONTH(C5),"-",YEAR(C5)) -> 6-2024 | E5: 45447 | F5: 45463 | G5: USD | H5: 1.4 | I5: Regular Cash | J5: =INDEX('CI - Stock PX'!C:C,MATCH(D5,'CI - Stock PX'!B:B,0)) -> 330.18
A6: 16) | B6: 45324 | C6: 45356 | D6: =_xlfn.CONCAT(MONTH(C6),"-",YEAR(C6)) -> 3-2024 | E6: 45357 | F6: 45372 | G6: USD | H6: 1.4 | I6: Regular Cash | J6: =INDEX('CI - Stock PX'!C:C,MATCH(D6,'CI - Stock PX'!B:B,0)) -> 363.19
A7: 17) | B7: 45224 | C7: 45265 | D7: =_xlfn.CONCAT(MONTH(C7),"-",YEAR(C7)) -> 12-2023 | E7: 45266 | F7: 45281 | G7: USD | H7: 1.23 | I7: Regular Cash | J7: =INDEX('CI - Stock PX'!C:C,MATCH(D7,'CI - Stock PX'!B:B,0)) -> 299.51
A8: 18) | B8: 45133 | C8: 45174 | D8: =_xlfn.CONCAT(MONTH(C8),"-",YEAR(C8)) -> 9-2023 | E8: 45175 | F8: 45190 | G8: USD | H8: 1.23 | I8: Regular Cash | J8: =INDEX('CI - Stock PX'!C:C,MATCH(D8,'CI - Stock PX'!B:B,0)) -> 286.08
A9: 19) | B9: 45042 | C9: 45083 | D9: =_xlfn.CONCAT(MONTH(C9),"-",YEAR(C9)) -> 6-2023 | E9: 45084 | F9: 45099 | G9: USD | H9: 1.23 | I9: Regular Cash | J9: =INDEX('CI - Stock PX'!C:C,MATCH(D9,'CI - Stock PX'!B:B,0)) -> 280.51
A10: 20) | B10: 44960 | C10: 44992 | D10: =_xlfn.CONCAT(MONTH(C10),"-",YEAR(C10)) -> 3-2023 | E10: 44993 | F10: 45008 | G10: USD | H10: 1.23 | I10: Regular Cash | J10: =INDEX('CI - Stock PX'!C:C,MATCH(D10,'CI - Stock PX'!B:B,0)) -> 255.31
A11: 21) | B11: 44860 | C11: 44900 | D11: =_xlfn.CONCAT(MONTH(C11),"-",YEAR(C11)) -> 12-2022 | E11: 44901 | F11: 44916 | G11: USD | H11: 1.12 | I11: Regular Cash | J11: =INDEX('CI - Stock PX'!C:C,MATCH(D11,'CI - Stock PX'!B:B,0)) -> 331.37
A12: 22) | B12: 44769 | C12: 44810 | D12: =_xlfn.CONCAT(MONTH(C12),"-",YEAR(C12)) -> 9-2022 | E12: 44811 | F12: 44826 | G12: USD | H12: 1.12 | I12: Regular Cash | J12: =INDEX('CI - Stock PX'!C:C,MATCH(D12,'CI - Stock PX'!B:B,0)) -> 277.7
A13: 23) | B13: 44678 | C13: 44719 | D13: =_xlfn.CONCAT(MONTH(C13),"-",YEAR(C13)) -> 6-2022 | E13: 44720 | F13: 44735 | G13: USD | H13: 1.12 | I13: Regular Cash | J13: =INDEX('CI - Stock PX'!C:C,MATCH(D13,'CI - Stock PX'!B:B,0)) -> 263.54
... A19: 29) | B19: 43887 | C19: 43899 | D19: =_xlfn.CONCAT(MONTH(C19),"-",YEAR(C19)) -> 3-2020 | E19: 43900 | F19: 43930 | G19: USD | H19: 0.04 | I19: Regular Cash | J19: =INDEX('CI - Stock PX'!C:C,MATCH(D19,'CI - Stock PX'!B:B,0)) -> 176.8
H20: =AVERAGE(H2:H19) -> 1.1416667

Sheet KMB - Stock PX
A1: Security | B1: KMB US Equity
A2: Start Date | B2: 43553
A3: End Date | B3: 45747
A4: Period | B4: M
A5: Currency | B5: USD
A7: Date | B7: Lookup Date | C7: PX_LAST | D7: Dividends | E7: PX_Change | F7: Risk Free (10yrbd) | G7: Return
A8: 45747 | B8: =_xlfn.CONCAT(MONTH(A8),"-",YEAR(A8)) -> 3-2025 | C8: 142.22 | D8: =IFERROR(INDEX('KMB - Dividends '!H:H,MATCH(B8,'KMB - Dividends '!D:D,0)),0) -> 1.26 | E8: =((C8+D8)-(C9+D9))/(C8+D8) -> 0.01024533 | F8: =INDEX('10YR Treasury'!E:E,MATCH(B8,'10YR Treasury'!B:B,0)) -> 0.0035044167 | G8: =E8-F8 -> 0.0067409137
A9: 45716 | B9: =_xlfn.CONCAT(MONTH(A9),"-",YEAR(A9)) -> 2-2025 | C9: 142.01 | D9: =IFERROR(INDEX('KMB - Dividends '!H:H,MATCH(B9,'KMB - Dividends '!D:D,0)),0) -> 0 | E9: =((C9+D9)-(C10+D10))/(C9+D9) -> 0.084782762 | F9: =INDEX('10YR Treasury'!E:E,MATCH(B9,'10YR Treasury'!B:B,0)) -> 0.0035068333 | G9: =E9-F9 -> 0.081275928
A10: 45688 | B10: =_xlfn.CONCAT(MONTH(A10),"-",YEAR(A10)) -> 1-2025 | C10: 129.97 | D10: =IFERROR(INDEX('KMB - Dividends '!H:H,MATCH(B10,'KMB - Dividends '!D:D,0)),0) -> 0 | E10: =((C10+D10)-(C11+D11))/(C10+D10) -> -0.017619451 | F10: =INDEX('10YR Treasury'!E:E,MATCH(B10,'10YR Treasury'!B:B,0)) -> 0.00378225 | G10: =E10-F10 -> -0.021401701
A11: 45657 | B11: =_xlfn.CONCAT(MONTH(A11),"-",YEAR(A11)) -> 12-2024 | C11: 131.04 | D11: =IFERROR(INDEX('KMB - Dividends '!H:H,MATCH(B11,'KMB - Dividends '!D:D,0)),0) -> 1.22 | E11: =((C11+D11)-(C12+D12))/(C11+D11) -> -0.053606533 | F11: =INDEX('10YR Treasury'!E:E,MATCH(B11,'10YR Treasury'!B:B,0)) -> 0.0038075 | G11: =E11-F11 -> -0.057414033
A12: 45625 | B12: =_xlfn.CONCAT(MONTH(A12),"-",YEAR(A12)) -> 11-2024 | C12: 139.35 | D12: =IFERROR(INDEX('KMB - Dividends '!H:H,MATCH(B12,'KMB - Dividends '!D:D,0)),0) -> 0 | E12: =((C12+D12)-(C13+D13))/(C12+D12) -> 0.037100825 | F12: =INDEX('10YR Treasury'!E:E,MATCH(B12,'10YR Treasury'!B:B,0)) -> 0.00347375 | G12: =E12-F12 -> 0.033627075
A13: 45596 | B13: =_xlfn.CONCAT(MONTH(A13),"-",YEAR(A13)) -> 10-2024 | C13: 134.18 | D13: =IFERROR(INDEX('KMB - Dividends '!H:H,MATCH(B13,'KMB - Dividends '!D:D,0)),0) -> 0 | E13: =((C13+D13)-(C14+D14))/(C13+D13) -> -0.069458936 | F13: =INDEX('10YR Treasury'!E:E,MATCH(B13,'10YR Treasury'!B:B,0)) -> 0.0035703333 | G13: =E13-F13 -> -0.073029269
A14: 45565 | B14: =_xlfn.CONCAT(MONTH(A14),"-",YEAR(A14)) -> 9-2024 | C14: 142.28 | D14: =IFERROR(INDEX('KMB - Dividends '!H:H,MATCH(B14,'KMB - Dividends '!D:D,0)),0) -> 1.22 | E14: =((C14+D14)-(C15+D15))/(C14+D14) -> -0.0080836237 | F14: =INDEX('10YR Treasury'!E:E,MATCH(B14,'10YR Treasury'!B:B,0)) -> 0.00315075 | G14: =E14-F14 -> -0.011234374
A15: 45534 | B15: =_xlfn.CONCAT(MONTH(A15),"-",YEAR(A15)) -> 8-2024 | C15: 144.66 | D15: =IFERROR(INDEX('KMB - Dividends '!H:H,MATCH(B15,'KMB - Dividends '!D:D,0)),0) -> 0 | E15: =((C15+D15)-(C16+D16))/(C15+D15) -> 0.066431633 | F15: =INDEX('10YR Treasury'!E:E,MATCH(B15,'10YR Treasury'!B:B,0)) -> 0.0032528333 | G15: =E15-F15 -> 0.063178799
A16: 45504 | B16: =_xlfn.CONCAT(MONTH(A16),"-",YEAR(A16)) -> 7-2024 | C16: 135.05 | D16: =IFERROR(INDEX('KMB - Dividends '!H:H,MATCH(B16,'KMB - Dividends '!D:D,0)),0) -> 0 | E16: =((C16+D16)-(C17+D17))/(C16+D16) -> -0.032358386 | F16: =INDEX('10YR Treasury'!E:E,MATCH(B16,'10YR Treasury'!B:B,0)) -> 0.003358 | G16: =E16-F16 -> -0.035716386
A17: 45471 | B17: =_xlfn.CONCAT(MONTH(A17),"-",YEAR(A17)) -> 6-2024 | C17: 138.2 | D17: =IFERROR(INDEX('KMB - Dividends '!H:H,MATCH(B17,'KMB - Dividends '!D:D,0)),0) -> 1.22 | E17: =((C17+D17)-(C18+D18))/(C17+D17) -> 0.043896141 | F17: =INDEX('10YR Treasury'!E:E,MATCH(B17,'10YR Treasury'!B:B,0)) -> 0.0036634167 | G17: =E17-F17 -> 0.040232724
A18: 45443 | B18: =_xlfn.CONCAT(MONTH(A18),"-",YEAR(A18)) -> 5-2024 | C18: 133.3 | D18: =IFERROR(INDEX('KMB - Dividends '!H:H,MATCH(B18,'KMB - Dividends '!D:D,0)),0) -> 0 | E18: =((C18+D18)-(C19+D19))/(C18+D18) -> -0.024231058 | F18: =INDEX('10YR Treasury'!E:E,MATCH(B18,'10YR Treasury'!B:B,0)) -> 0.00374875 | G18: =E18-F18 -> -0.027979808
A19: 45412 | B19: =_xlfn.CONCAT(MONTH(A19),"-",YEAR(A19)) -> 4-2024 | C19: 136.53 | D19: =IFERROR(INDEX('KMB - Dividends '!H:H,MATCH(B19,'KMB - Dividends '!D:D,0)),0) -> 0 | E19: =((C19+D19)-(C20+D20))/(C19+D19) -> 0.04365341 | F19: =INDEX('10YR Treasury'!E:E,MATCH(B19,'10YR Treasury'!B:B,0)) -> 0.0038998333 | G19: =E19-F19 -> 0.039753576
... A67: 43951 | B67: =_xlfn.CONCAT(MONTH(A67),"-",YEAR(A67)) -> 4-2020 | C67: 138.48 | D67: =IFERROR(INDEX('KMB - Dividends '!H:H,MATCH(B67,'KMB - Dividends '!D:D,0)),0) -> 0 | E67: =((C67+D67)-(C68+D68))/(C67+D67) -> 0.068890815 | F67: =INDEX('10YR Treasury'!E:E,MATCH(B67,'10YR Treasury'!B:B,0)) -> 0.00053275 | G67: =E67-F67 -> 0.068358065
A68: 43921 | B68: =_xlfn.CONCAT(MONTH(A68),"-",YEAR(A68)) -> 3-2020 | C68: 127.87 | D68: =IFERROR(INDEX('KMB - Dividends '!H:H,MATCH(B68,'KMB - Dividends '!D:D,0)),0) -> 1.07 | F68: =INDEX('10YR Treasury'!E:E,MATCH(B68,'10YR Treasury'!B:B,0)) -> 0.00055791667
B69: AVG | C69: =AVERAGE(C9:C68) -> 133.55183 | E69: =AVERAGE(E9:E68) -> 0.00015771709 | F69: =INDEX('10YR Treasury'!E:E,MATCH(B69,'10YR Treasury'!B:B,0)) -> 0.0023233374 | G69: =AVERAGE(G9:G68) -> -0.0021986798
B70: SD | C70: =STDEV(C9:C68) -> 8.0765466 | E70: =STDEV(E9:E68) -> 0.054719159 | F70: =INDEX('10YR Treasury'!E:E,MATCH(B70,'10YR Treasury'!B:B,0)) -> #N/A | G70: =STDEV(G9:G68) -> 0.054733304

Sheet KMB - Dividends 
B1: Declaration | C1: Ex Date | D1: Lookup Date | E1: record | F1: Payable | G1: Curr | H1: Amount | I1: Type | J1: quarter end price
A3: 12) | B3: 45685 | C3: 45723 | D3: =_xlfn.CONCAT(MONTH(C3),"-",YEAR(C3)) -> 3-2025 | E3: 45723 | F3: 45749 | G3: USD | H3: 1.26 | I3: Regular Cash | J3: =INDEX('KMB - Stock PX'!C:C,MATCH(D3,'KMB - Stock PX'!B:B,0)) -> 142.22
A4: 13) | B4: 45609 | C4: 45632 | D4: =_xlfn.CONCAT(MONTH(C4),"-",YEAR(C4)) -> 12-2024 | E4: 45632 | F4: 45660 | G4: USD | H4: 1.22 | I4: Regular Cash | J4: =INDEX('KMB - Stock PX'!C:C,MATCH(D4,'KMB - Stock PX'!B:B,0)) -> 131.04
A5: 14) | B5: 45505 | C5: 45541 | D5: =_xlfn.CONCAT(MONTH(C5),"-",YEAR(C5)) -> 9-2024 | E5: 45541 | F5: 45567 | G5: USD | H5: 1.22 | I5: Regular Cash | J5: =INDEX('KMB - Stock PX'!C:C,MATCH(D5,'KMB - Stock PX'!B:B,0)) -> 142.28
A6: 15) | B6: 45414 | C6: 45450 | D6: =_xlfn.CONCAT(MONTH(C6),"-",YEAR(C6)) -> 6-2024 | E6: 45450 | F6: 45475 | G6: USD | H6: 1.22 | I6: Regular Cash | J6: =INDEX('KMB - Stock PX'!C:C,MATCH(D6,'KMB - Stock PX'!B:B,0)) -> 138.2
A7: 16) | B7: 45315 | C7: 45358 | D7: =_xlfn.CONCAT(MONTH(C7),"-",YEAR(C7)) -> 3-2024 | E7: 45359 | F7: 45384 | G7: USD | H7: 1.22 | I7: Regular Cash | J7: =INDEX('KMB - Stock PX'!C:C,MATCH(D7,'KMB - Stock PX'!B:B,0)) -> 129.35
A8: 17) | B8: 45246 | C8: 45267 | D8: =_xlfn.CONCAT(MONTH(C8),"-",YEAR(C8)) -> 12-2023 | E8: 45268 | F8: 45294 | G8: USD | H8: 1.18 | I8: Regular Cash | J8: =INDEX('KMB - Stock PX'!C:C,MATCH(D8,'KMB - Stock PX'!B:B,0)) -> 121.51
A9: 18) | B9: 45139 | C9: 45176 | D9: =_xlfn.CONCAT(MONTH(C9),"-",YEAR(C9)) -> 9-2023 | E9: 45177 | F9: 45202 | G9: USD | H9: 1.18 | I9: Regular Cash | J9: =INDEX('KMB - Stock PX'!C:C,MATCH(D9,'KMB - Stock PX'!B:B,0)) -> 120.85
A10: 19) | B10: 45036 | C10: 45085 | D10: =_xlfn.CONCAT(MONTH(C10),"-",YEAR(C10)) -> 6-2023 | E10: 45086 | F10: 45112 | G10: USD | H10: 1.18 | I10: Regular Cash | J10: =INDEX('KMB - Stock PX'!C:C,MATCH(D10,'KMB - Stock PX'!B:B,0)) -> 138.06
A11: 20) | B11: 44951 | C11: 44994 | D11: =_xlfn.CONCAT(MONTH(C11),"-",YEAR(C11)) -> 3-2023 | E11: 44995 | F11: 45020 | G11: USD | H11: 1.18 | I11: Regular Cash | J11: =INDEX('KMB - Stock PX'!C:C,MATCH(D11,'KMB - Stock PX'!B:B,0)) -> 134.22
A12: 21) | B12: 44882 | C12: 44903 | D12: =_xlfn.CONCAT(MONTH(C12),"-",YEAR(C12)) -> 12-2022 | E12: 44904 | F12: 44930 | G12: USD | H12: 1.16 | I12: Regular Cash | J12: =INDEX('KMB - Stock PX'!C:C,MATCH(D12,'KMB - Stock PX'!B:B,0)) -> 135.75
A13: 22) | B13: 44774 | C13: 44812 | D13: =_xlfn.CONCAT(MONTH(C13),"-",YEAR(C13)) -> 9-2022 | E13: 44813 | F13: 44838 | G13: USD | H13: 1.16 | I13: Regular Cash | J13: =INDEX('KMB - Stock PX'!C:C,MATCH(D13,'KMB - Stock PX'!B:B,0)) -> 112.54
A14: 23) | B14: 44678 | C14: 44721 | D14: =_xlfn.CONCAT(MONTH(C14),"-",YEAR(C14)) -> 6-2022 | E14: 44722 | F14: 44747 | G14: USD | H14: 1.16 | I14: Regular Cash | J14: =INDEX('KMB - Stock PX'!C:C,MATCH(D14,'KMB - Stock PX'!B:B,0)) -> 135.15
... A23: 32) | B23: 43853 | C23: 43895 | D23: =_xlfn.CONCAT(MONTH(C23),"-",YEAR(C23)) -> 3-2020 | E23: 43896 | F23: 43923 | G23: USD | H23: 1.07 | I23: Regular Cash | J23: =INDEX('KMB - Stock PX'!C:C,MATCH(D23,'KMB - Stock PX'!B:B,0)) -> 127.87
H24: =AVERAGE(H3:H23) -> 1.1590476

Sheet EBAY - Stock PX
A1: Security | B1: EBAY US Equity
A2: Start Date | B2: 43553
A3: End Date | B3: 45747
A4: Period | B4: M
A5: Currency | B5: USD
A7: Date | B7: Lookup Date | C7: PX_LAST | D7: Dividends | E7: PX_Change | F7: Risk Free (10yrbd) | G7: Return
A8: 45747 | B8: =_xlfn.CONCAT(MONTH(A8),"-",YEAR(A8)) -> 3-2025 | C8: 67.73 | D8: =IFERROR(INDEX('EBAY - Dividends'!H:H,MATCH(B8,'EBAY - Dividends'!D:D,0)),0) -> 0.29 | E8: =((C8+D8)-(C9+D9))/(C8+D8) -> 0.048221111 | F8: =INDEX('10YR Treasury'!E:E,MATCH(B8,'10YR Treasury'!B:B,0)) -> 0.0035044167 | G8: =E8-F8 -> 0.044716695
A9: 45716 | B9: =_xlfn.CONCAT(MONTH(A9),"-",YEAR(A9)) -> 2-2025 | C9: 64.74 | D9: =IFERROR(INDEX('EBAY - Dividends'!H:H,MATCH(B9,'EBAY - Dividends'!D:D,0)),0) -> 0 | E9: =((C9+D9)-(C10+D10))/(C9+D9) -> -0.042323139 | F9: =INDEX('10YR Treasury'!E:E,MATCH(B9,'10YR Treasury'!B:B,0)) -> 0.0035068333 | G9: =E9-F9 -> -0.045829972
A10: 45688 | B10: =_xlfn.CONCAT(MONTH(A10),"-",YEAR(A10)) -> 1-2025 | C10: 67.48 | D10: =IFERROR(INDEX('EBAY - Dividends'!H:H,MATCH(B10,'EBAY - Dividends'!D:D,0)),0) -> 0 | E10: =((C10+D10)-(C11+D11))/(C10+D10) -> 0.081950207 | F10: =INDEX('10YR Treasury'!E:E,MATCH(B10,'10YR Treasury'!B:B,0)) -> 0.00378225 | G10: =E10-F10 -> 0.078167957
A11: 45657 | B11: =_xlfn.CONCAT(MONTH(A11),"-",YEAR(A11)) -> 12-2024 | C11: 61.95 | D11: =IFERROR(INDEX('EBAY - Dividends'!H:H,MATCH(B11,'EBAY - Dividends'!D:D,0)),0) -> 0 | E11: =((C11+D11)-(C12+D12))/(C11+D11) -> -0.025988701 | F11: =INDEX('10YR Treasury'!E:E,MATCH(B11,'10YR Treasury'!B:B,0)) -> 0.0038075 | G11: =E11-F11 -> -0.029796201
A12: 45625 | B12: =_xlfn.CONCAT(MONTH(A12),"-",YEAR(A12)) -> 11-2024 | C12: 63.29 | D12: =IFERROR(INDEX('EBAY - Dividends'!H:H,MATCH(B12,'EBAY - Dividends'!D:D,0)),0) -> 0.27 | E12: =((C12+D12)-(C13+D13))/(C12+D12) -> 0.095185651 | F12: =INDEX('10YR Treasury'!E:E,MATCH(B12,'10YR Treasury'!B:B,0)) -> 0.00347375 | G12: =E12-F12 -> 0.091711901
A13: 45596 | B13: =_xlfn.CONCAT(MONTH(A13),"-",YEAR(A13)) -> 10-2024 | C13: 57.51 | D13: =IFERROR(INDEX('EBAY - Dividends'!H:H,MATCH(B13,'EBAY - Dividends'!D:D,0)),0) -> 0 | E13: =((C13+D13)-(C14+D14))/(C13+D13) -> -0.13215093 | F13: =INDEX('10YR Treasury'!E:E,MATCH(B13,'10YR Treasury'!B:B,0)) -> 0.0035703333 | G13: =E13-F13 -> -0.13572126
A14: 45565 | B14: =_xlfn.CONCAT(MONTH(A14),"-",YEAR(A14)) -> 9-2024 | C14: 65.11 | D14: =IFERROR(INDEX('EBAY - Dividends'!H:H,MATCH(B14,'EBAY - Dividends'!D:D,0)),0) -> 0 | E14: =((C14+D14)-(C15+D15))/(C14+D14) -> 0.088158501 | F14: =INDEX('10YR Treasury'!E:E,MATCH(B14,'10YR Treasury'!B:B,0)) -> 0.00315075 | G14: =E14-F14 -> 0.085007751
A15: 45534 | B15: =_xlfn.CONCAT(MONTH(A15),"-",YEAR(A15)) -> 8-2024 | C15: 59.1 | D15: =IFERROR(INDEX('EBAY - Dividends'!H:H,MATCH(B15,'EBAY - Dividends'!D:D,0)),0) -> 0.27 | E15: =((C15+D15)-(C16+D16))/(C15+D15) -> 0.063331649 | F15: =INDEX('10YR Treasury'!E:E,MATCH(B15,'10YR Treasury'!B:B,0)) -> 0.0032528333 | G15: =E15-F15 -> 0.060078816
A16: 45504 | B16: =_xlfn.CONCAT(MONTH(A16),"-",YEAR(A16)) -> 7-2024 | C16: 55.61 | D16: =IFERROR(INDEX('EBAY - Dividends'!H:H,MATCH(B16,'EBAY - Dividends'!D:D,0)),0) -> 0 | E16: =((C16+D16)-(C17+D17))/(C16+D16) -> 0.033986693 | F16: =INDEX('10YR Treasury'!E:E,MATCH(B16,'10YR Treasury'!B:B,0)) -> 0.003358 | G16: =E16-F16 -> 0.030628693
A17: 45471 | B17: =_xlfn.CONCAT(MONTH(A17),"-",YEAR(A17)) -> 6-2024 | C17: 53.72 | D17: =IFERROR(INDEX('EBAY - Dividends'!H:H,MATCH(B17,'EBAY - Dividends'!D:D,0)),0) -> 0 | E17: =((C17+D17)-(C18+D18))/(C17+D17) -> -0.014333582 | F17: =INDEX('10YR Treasury'!E:E,MATCH(B17,'10YR Treasury'!B:B,0)) -> 0.0036634167 | G17: =E17-F17 -> -0.017996998
A18: 45443 | B18: =_xlfn.CONCAT(MONTH(A18),"-",YEAR(A18)) -> 5-2024 | C18: 54.22 | D18: =IFERROR(INDEX('EBAY - Dividends'!H:H,MATCH(B18,'EBAY - Dividends'!D:D,0)),0) -> 0.27 | E18: =((C18+D18)-(C19+D19))/(C18+D18) -> 0.054138374 | F18: =INDEX('10YR Treasury'!E:E,MATCH(B18,'10YR Treasury'!B:B,0)) -> 0.00374875 | G18: =E18-F18 -> 0.050389624
A19: 45412 | B19: =_xlfn.CONCAT(MONTH(A19),"-",YEAR(A19)) -> 4-2024 | C19: 51.54 | D19: =IFERROR(INDEX('EBAY - Dividends'!H:H,MATCH(B19,'EBAY - Dividends'!D:D,0)),0) -> 0 | E19: =((C19+D19)-(C20+D20))/(C19+D19) -> -0.029297633 | F19: =INDEX('10YR Treasury'!E:E,MATCH(B19,'10YR Treasury'!B:B,0)) -> 0.0038998333 | G19: =E19-F19 -> -0.033197466
... A66: 43980 | B66: =_xlfn.CONCAT(MONTH(A66),"-",YEAR(A66)) -> 5-2020 | C66: 45.54 | D66: =IFERROR(INDEX('EBAY - Dividends'!H:H,MATCH(B66,'EBAY - Dividends'!D:D,0)),0) -> 0.16 | E66: =((C66+D66)-(C67+D67))/(C66+D66) -> 0.12844639 | F66: =INDEX('10YR Treasury'!E:E,MATCH(B66,'10YR Treasury'!B:B,0)) -> 0.00054383333 | G66: =E66-F66 -> 0.12790256
A67: 43951 | B67: =_xlfn.CONCAT(MONTH(A67),"-",YEAR(A67)) -> 4-2020 | C67: 39.83 | D67: =IFERROR(INDEX('EBAY - Dividends'!H:H,MATCH(B67,'EBAY - Dividends'!D:D,0)),0) -> 0 | F67: =INDEX('10YR Treasury'!E:E,MATCH(B67,'10YR Treasury'!B:B,0)) -> 0.00053275
B68: AVG | C68: =AVERAGE(C8:C67) -> 53.315667 | E68: =AVERAGE(E8:E67) -> 0.0049795291 | F68: =AVERAGE(F8:F67) -> 0.0023755306 | G68: =AVERAGE(G8:G67) -> 0.002572765
B69: SD | C69: =STDEV(C8:C67) -> 9.9510351 | E69: =STDEV(E8:E67) -> 0.090896594 | F69: =STDEV(F8:F67) -> 0.0011818054 | G69: =STDEV(G8:G67) -> 0.090983208
B70: total | C70: =(C8-C67)/C67 -> 0.70047703

Sheet EBAY - Dividends
A3: EBAY US Equity Settings Dividend/Split Summary
A4: eBay Inc
B5: Declaration | C5: Ex Date | D5: Lookup Date | E5: Record | F5: Payable | G5: Curr | H5: Amount | I5: Type | J5: quarter end price
A6: 12) | B6: 45714 | C6: 45730 | D6: =_xlfn.CONCAT(MONTH(C6),"-",YEAR(C6)) -> 3-2025 | E6: 45730 | F6: 45744 | G6: USD | H6: 0.29 | I6: Regular Cash | J6: =INDEX('EBAY - Stock PX'!C:C,MATCH(D6,'EBAY - Stock PX'!B:B,0)) -> 67.73
A7: 13) | B7: 45595 | C7: 45625 | D7: =_xlfn.CONCAT(MONTH(C7),"-",YEAR(C7)) -> 11-2024 | E7: 45625 | F7: 45639 | G7: USD | H7: 0.27 | I7: Regular Cash | J7: =INDEX('EBAY - Stock PX'!C:C,MATCH(D7,'EBAY - Stock PX'!B:B,0)) -> 63.29
A8: 14) | B8: 45504 | C8: 45534 | D8: =_xlfn.CONCAT(MONTH(C8),"-",YEAR(C8)) -> 8-2024 | E8: 45534 | F8: 45548 | G8: USD | H8: 0.27 | I8: Regular Cash | J8: =INDEX('EBAY - Stock PX'!C:C,MATCH(D8,'EBAY - Stock PX'!B:B,0)) -> 59.1
A9: 15) | B9: 45413 | C9: 45443 | D9: =_xlfn.CONCAT(MONTH(C9),"-",YEAR(C9)) -> 5-2024 | E9: 45443 | F9: 45457 | G9: USD | H9: 0.27 | I9: Regular Cash | J9: =INDEX('EBAY - Stock PX'!C:C,MATCH(D9,'EBAY - Stock PX'!B:B,0)) -> 54.22
A10: 16) | B10: 45349 | C10: 45359 | D10: =_xlfn.CONCAT(MONTH(C10),"-",YEAR(C10)) -> 3-2024 | E10: 45362 | F10: 45376 | G10: USD | H10: 0.27 | I10: Regular Cash | J10: =INDEX('EBAY - Stock PX'!C:C,MATCH(D10,'EBAY - Stock PX'!B:B,0)) -> 52.78
A11: 17) | B11: 45237 | C11: 45260 | D11: =_xlfn.CONCAT(MONTH(C11),"-",YEAR(C11)) -> 11-2023 | E11: 45261 | F11: 45275 | G11: USD | H11: 0.25 | I11: Regular Cash | J11: =INDEX('EBAY - Stock PX'!C:C,MATCH(D11,'EBAY - Stock PX'!B:B,0)) -> 41.01
A12: 18) | B12: 45133 | C12: 45169 | D12: =_xlfn.CONCAT(MONTH(C12),"-",YEAR(C12)) -> 8-2023 | E12: 45170 | F12: 45184 | G12: USD | H12: 0.25 | I12: Regular Cash | J12: =INDEX('EBAY - Stock PX'!C:C,MATCH(D12,'EBAY - Stock PX'!B:B,0)) -> 44.78
A13: 19) | B13: 45042 | C13: 45077 | D13: =_xlfn.CONCAT(MONTH(C13),"-",YEAR(C13)) -> 5-2023 | E13: 45078 | F13: 45093 | G13: USD | H13: 0.25 | I13: Regular Cash | J13: =INDEX('EBAY - Stock PX'!C:C,MATCH(D13,'EBAY - Stock PX'!B:B,0)) -> 42.54
A14: 20) | B14: 44979 | C14: 44994 | D14: =_xlfn.CONCAT(MONTH(C14),"-",YEAR(C14)) -> 3-2023 | E14: 44995 | F14: 45009 | G14: USD | H14: 0.25 | I14: Regular Cash | J14: =INDEX('EBAY - Stock PX'!C:C,MATCH(D14,'EBAY - Stock PX'!B:B,0)) -> 44.37
A15: 21) | B15: 44867 | C15: 44895 | D15: =_xlfn.CONCAT(MONTH(C15),"-",YEAR(C15)) -> 11-2022 | E15: 44896 | F15: 44911 | G15: USD | H15: 0.22 | I15: Regular Cash | J15: =INDEX('EBAY - Stock PX'!C:C,MATCH(D15,'EBAY - Stock PX'!B:B,0)) -> 45.44
A16: 22) | B16: 44776 | C16: 44804 | D16: =_xlfn.CONCAT(MONTH(C16),"-",YEAR(C16)) -> 8-2022 | E16: 44805 | F16: 44820 | G16: USD | H16: 0.22 | I16: Regular Cash | J16: =INDEX('EBAY - Stock PX'!C:C,MATCH(D16,'EBAY - Stock PX'!B:B,0)) -> 44.13
A17: 23) | B17: 44685 | C17: 44712 | D17: =_xlfn.CONCAT(MONTH(C17),"-",YEAR(C17)) -> 5-2022 | E17: 44713 | F17: 44729 | G17: USD | H17: 0.22 | I17: Regular Cash | J17: =INDEX('EBAY - Stock PX'!C:C,MATCH(D17,'EBAY - Stock PX'!B:B,0)) -> 48.67
... A25: 31) | B25: 43950 | C25: 43980 | D25: =_xlfn.CONCAT(MONTH(C25),"-",YEAR(C25)) -> 5-2020 | E25: 43983 | F25: 44001 | G25: USD | H25: 0.16 | I25: Regular Cash | J25: =INDEX('EBAY - Stock PX'!C:C,MATCH(D25,'EBAY - Stock PX'!B:B,0)) -> 45.54
H26: =AVERAGE(H6:H25) -> 0.2225

Sheet CAT - Stock PX
A1: Security | B1: CAT US Equity
A2: Start Date | B2: 43553
A3: End Date | B3: 45747
A4: Period | B4: M
A5: Currency | B5: USD
A7: Date | B7: Lookup Date | C7: PX_LAST | D7: Dividends | E7: PX_CHANGE | F7: Risk Free (10yrbd) | G7: Excess Return
A8: 45747 | B8: =_xlfn.CONCAT(MONTH(A8),"-",YEAR(A8)) -> 3-2025 | C8: 329.8 | D8: =IFERROR(INDEX('CAT - Dividends'!H:H,MATCH(B8,'CAT - Dividends'!D:D,0)),0) -> 0 | E8: =((C8+D8)-(C9+D9))/(C8+D8) -> -0.042904791 | F8: =INDEX('10YR Treasury'!E:E,MATCH(B8,'10YR Treasury'!B:B,0)) -> 0.0035044167 | G8: =E8-F8 -> -0.046409207
A9: 45716 | B9: =_xlfn.CONCAT(MONTH(A9),"-",YEAR(A9)) -> 2-2025 | C9: 343.95 | D9: =IFERROR(INDEX('CAT - Dividends'!H:H,MATCH(B9,'CAT - Dividends'!D:D,0)),0) -> 0 | E9: =((C9+D9)-(C10+D10))/(C9+D9) -> -0.084023841 | F9: =INDEX('10YR Treasury'!E:E,MATCH(B9,'10YR Treasury'!B:B,0)) -> 0.0035068333 | G9: =E9-F9 -> -0.087530674
A10: 45688 | B10: =_xlfn.CONCAT(MONTH(A10),"-",YEAR(A10)) -> 1-2025 | C10: 371.44 | D10: =IFERROR(INDEX('CAT - Dividends'!H:H,MATCH(B10,'CAT - Dividends'!D:D,0)),0) -> 1.41 | E10: =((C10+D10)-(C11+D11))/(C10+D10) -> 0.027061821 | F10: =INDEX('10YR Treasury'!E:E,MATCH(B10,'10YR Treasury'!B:B,0)) -> 0.00378225 | G10: =E10-F10 -> 0.023279571
A11: 45657 | B11: =_xlfn.CONCAT(MONTH(A11),"-",YEAR(A11)) -> 12-2024 | C11: 362.76 | D11: =IFERROR(INDEX('CAT - Dividends'!H:H,MATCH(B11,'CAT - Dividends'!D:D,0)),0) -> 0 | E11: =((C11+D11)-(C12+D12))/(C11+D11) -> -0.1195005 | F11: =INDEX('10YR Treasury'!E:E,MATCH(B11,'10YR Treasury'!B:B,0)) -> 0.0038075 | G11: =E11-F11 -> -0.123308
A12: 45625 | B12: =_xlfn.CONCAT(MONTH(A12),"-",YEAR(A12)) -> 11-2024 | C12: 406.11 | D12: =IFERROR(INDEX('CAT - Dividends'!H:H,MATCH(B12,'CAT - Dividends'!D:D,0)),0) -> 0 | E12: =((C12+D12)-(C13+D13))/(C12+D12) -> 0.070178031 | F12: =INDEX('10YR Treasury'!E:E,MATCH(B12,'10YR Treasury'!B:B,0)) -> 0.00347375 | G12: =E12-F12 -> 0.066704281
A13: 45596 | B13: =_xlfn.CONCAT(MONTH(A13),"-",YEAR(A13)) -> 10-2024 | C13: 376.2 | D13: =IFERROR(INDEX('CAT - Dividends'!H:H,MATCH(B13,'CAT - Dividends'!D:D,0)),0) -> 1.41 | E13: =((C13+D13)-(C14+D14))/(C13+D13) -> -0.035777654 | F13: =INDEX('10YR Treasury'!E:E,MATCH(B13,'10YR Treasury'!B:B,0)) -> 0.0035703333 | G13: =E13-F13 -> -0.039347988
A14: 45565 | B14: =_xlfn.CONCAT(MONTH(A14),"-",YEAR(A14)) -> 9-2024 | C14: 391.12 | D14: =IFERROR(INDEX('CAT - Dividends'!H:H,MATCH(B14,'CAT - Dividends'!D:D,0)),0) -> 0 | E14: =((C14+D14)-(C15+D15))/(C14+D14) -> 0.089537738 | F14: =INDEX('10YR Treasury'!E:E,MATCH(B14,'10YR Treasury'!B:B,0)) -> 0.00315075 | G14: =E14-F14 -> 0.086386988
A15: 45534 | B15: =_xlfn.CONCAT(MONTH(A15),"-",YEAR(A15)) -> 8-2024 | C15: 356.1 | D15: =IFERROR(INDEX('CAT - Dividends'!H:H,MATCH(B15,'CAT - Dividends'!D:D,0)),0) -> 0 | E15: =((C15+D15)-(C16+D16))/(C15+D15) -> 0.023841618 | F15: =INDEX('10YR Treasury'!E:E,MATCH(B15,'10YR Treasury'!B:B,0)) -> 0.0032528333 | G15: =E15-F15 -> 0.020588784
A16: 45504 | B16: =_xlfn.CONCAT(MONTH(A16),"-",YEAR(A16)) -> 7-2024 | C16: 346.2 | D16: =IFERROR(INDEX('CAT - Dividends'!H:H,MATCH(B16,'CAT - Dividends'!D:D,0)),0) -> 1.41 | E16: =((C16+D16)-(C17+D17))/(C16+D16) -> 0.041742182 | F16: =INDEX('10YR Treasury'!E:E,MATCH(B16,'10YR Treasury'!B:B,0)) -> 0.003358 | G16: =E16-F16 -> 0.038384182
A17: 45471 | B17: =_xlfn.CONCAT(MONTH(A17),"-",YEAR(A17)) -> 6-2024 | C17: 333.1 | D17: =IFERROR(INDEX('CAT - Dividends'!H:H,MATCH(B17,'CAT - Dividends'!D:D,0)),0) -> 0 | E17: =((C17+D17)-(C18+D18))/(C17+D17) -> -0.01627139 | F17: =INDEX('10YR Treasury'!E:E,MATCH(B17,'10YR Treasury'!B:B,0)) -> 0.0036634167 | G17: =E17-F17 -> -0.019934807
A18: 45443 | B18: =_xlfn.CONCAT(MONTH(A18),"-",YEAR(A18)) -> 5-2024 | C18: 338.52 | D18: =IFERROR(INDEX('CAT - Dividends'!H:H,MATCH(B18,'CAT - Dividends'!D:D,0)),0) -> 0 | E18: =((C18+D18)-(C19+D19))/(C18+D18) -> 0.0078281933 | F18: =INDEX('10YR Treasury'!E:E,MATCH(B18,'10YR Treasury'!B:B,0)) -> 0.00374875 | G18: =E18-F18 -> 0.0040794433
A19: 45412 | B19: =_xlfn.CONCAT(MONTH(A19),"-",YEAR(A19)) -> 4-2024 | C19: 334.57 | D19: =IFERROR(INDEX('CAT - Dividends'!H:H,MATCH(B19,'CAT - Dividends'!D:D,0)),0) -> 1.3 | E19: =((C19+D19)-(C20+D20))/(C19+D19) -> -0.090987584 | F19: =INDEX('10YR Treasury'!E:E,MATCH(B19,'10YR Treasury'!B:B,0)) -> 0.0038998333 | G19: =E19-F19 -> -0.094887418
... A66: 43980 | B66: =_xlfn.CONCAT(MONTH(A66),"-",YEAR(A66)) -> 5-2020 | C66: 120.13 | D66: =IFERROR(INDEX('CAT - Dividends'!H:H,MATCH(B66,'CAT - Dividends'!D:D,0)),0) -> 0 | E66: =((C66+D66)-(C67+D67))/(C66+D66) -> 0.022642138 | F66: =INDEX('10YR Treasury'!E:E,MATCH(B66,'10YR Treasury'!B:B,0)) -> 0.00054383333 | G66: =E66-F66 -> 0.022098304
A67: 43951 | B67: =_xlfn.CONCAT(MONTH(A67),"-",YEAR(A67)) -> 4-2020 | C67: 116.38 | D67: =IFERROR(INDEX('CAT - Dividends'!H:H,MATCH(B67,'CAT - Dividends'!D:D,0)),0) -> 1.03 | F67: =INDEX('10YR Treasury'!E:E,MATCH(B67,'10YR Treasury'!B:B,0)) -> 0.00053275
B68: AVG | C68: =AVERAGE(C8:C67) -> 242.688 | E68: =AVERAGE(E8:E67) -> 0.013502616 | F68: =AVERAGE(F8:F67) -> 0.0023755306 | G68: =AVERAGE(G8:G67) -> 0.011095852
B69: SD | C69: =STDEV(C8:C67) -> 74.759874 | E69: =STDEV(E8:E67) -> 0.087850658 | F69: =STDEV(F8:F67) -> 0.0011818054 | G69: =STDEV(G8:G67) -> 0.088002019

Sheet CAT - Dividends
B1: Declaration | C1: Ex Date | D1: lookup date | E1: Record | F1: Payable | G1: Curr | H1: Amount | I1: Type | J1: quarter end price
A2: 11) | B2: 45763 | C2: 45768 | D2: =_xlfn.CONCAT(MONTH(C2),"-",YEAR(C2)) -> 4-2025 | G2: USD | H2: 1.41 | I2: BDVD Projection | J2: =INDEX('CAT - Stock PX'!C:C,MATCH(D2,'CAT - Stock PX'!B:B,0)) -> #N/A
A3: 12) | B3: 45636 | C3: 45678 | D3: =_xlfn.CONCAT(MONTH(C3),"-",YEAR(C3)) -> 1-2025 | E3: 45678 | F3: 45708 | G3: USD | H3: 1.41 | I3: Regular Cash | J3: =INDEX('CAT - Stock PX'!C:C,MATCH(D3,'CAT - Stock PX'!B:B,0)) -> 371.44
A4: 13) | B4: 45574 | C4: 45586 | D4: =_xlfn.CONCAT(MONTH(C4),"-",YEAR(C4)) -> 10-2024 | E4: 45586 | F4: 45616 | G4: USD | H4: 1.41 | I4: Regular Cash | J4: =INDEX('CAT - Stock PX'!C:C,MATCH(D4,'CAT - Stock PX'!B:B,0)) -> 376.2
A5: 14) | B5: 45455 | C5: 45495 | D5: =_xlfn.CONCAT(MONTH(C5),"-",YEAR(C5)) -> 7-2024 | E5: 45495 | F5: 45524 | G5: USD | H5: 1.41 | I5: Regular Cash | J5: =INDEX('CAT - Stock PX'!C:C,MATCH(D5,'CAT - Stock PX'!B:B,0)) -> 346.2
A6: 15) | B6: 45392 | C6: 45401 | D6: =_xlfn.CONCAT(MONTH(C6),"-",YEAR(C6)) -> 4-2024 | E6: 45404 | F6: 45432 | G6: USD | H6: 1.3 | I6: Regular Cash | J6: =INDEX('CAT - Stock PX'!C:C,MATCH(D6,'CAT - Stock PX'!B:B,0)) -> 334.57
A7: 16) | B7: 45273 | C7: 45310 | D7: =_xlfn.CONCAT(MONTH(C7),"-",YEAR(C7)) -> 1-2024 | E7: 45313 | F7: 45342 | G7: USD | H7: 1.3 | I7: Regular Cash | J7: =INDEX('CAT - Stock PX'!C:C,MATCH(D7,'CAT - Stock PX'!B:B,0)) -> 300.31
A8: 17) | B8: 45210 | C8: 45219 | D8: =_xlfn.CONCAT(MONTH(C8),"-",YEAR(C8)) -> 10-2023 | E8: 45222 | F8: 45250 | G8: USD | H8: 1.3 | I8: Regular Cash | J8: =INDEX('CAT - Stock PX'!C:C,MATCH(D8,'CAT - Stock PX'!B:B,0)) -> 226.05
A9: 18) | B9: 45091 | C9: 45126 | D9: =_xlfn.CONCAT(MONTH(C9),"-",YEAR(C9)) -> 7-2023 | E9: 45127 | F9: 45156 | G9: USD | H9: 1.3 | I9: Regular Cash | J9: =INDEX('CAT - Stock PX'!C:C,MATCH(D9,'CAT - Stock PX'!B:B,0)) -> 265.17
A10: 19) | B10: 45028 | C10: 45037 | D10: =_xlfn.CONCAT(MONTH(C10),"-",YEAR(C10)) -> 4-2023 | E10: 45040 | F10: 45065 | G10: USD | H10: 1.2 | I10: Regular Cash | J10: =INDEX('CAT - Stock PX'!C:C,MATCH(D10,'CAT - Stock PX'!B:B,0)) -> 218.8
A11: 20) | B11: 44909 | C11: 44945 | D11: =_xlfn.CONCAT(MONTH(C11),"-",YEAR(C11)) -> 1-2023 | E11: 44946 | F11: 44974 | G11: USD | H11: 1.2 | I11: Regular Cash | J11: =INDEX('CAT - Stock PX'!C:C,MATCH(D11,'CAT - Stock PX'!B:B,0)) -> 252.29
A12: 21) | B12: 44846 | C12: 44855 | D12: =_xlfn.CONCAT(MONTH(C12),"-",YEAR(C12)) -> 10-2022 | E12: 44858 | F12: 44883 | G12: USD | H12: 1.2 | I12: Regular Cash | J12: =INDEX('CAT - Stock PX'!C:C,MATCH(D12,'CAT - Stock PX'!B:B,0)) -> 216.46
A13: 22) | B13: 44720 | C13: 44761 | D13: =_xlfn.CONCAT(MONTH(C13),"-",YEAR(C13)) -> 7-2022 | E13: 44762 | F13: 44792 | G13: USD | H13: 1.2 | I13: Regular Cash | J13: =INDEX('CAT - Stock PX'!C:C,MATCH(D13,'CAT - Stock PX'!B:B,0)) -> 198.25
A14: 23) | B14: 44664 | C14: 44673 | D14: =_xlfn.CONCAT(MONTH(C14),"-",YEAR(C14)) -> 4-2022 | E14: 44676 | F14: 44701 | G14: USD | H14: 1.11 | I14: Regular Cash | J14: =INDEX('CAT - Stock PX'!C:C,MATCH(D14,'CAT - Stock PX'!B:B,0)) -> 210.54
... A22: 31) | B22: 43929 | C22: 43938 | D22: =_xlfn.CONCAT(MONTH(C22),"-",YEAR(C22)) -> 4-2020 | E22: 43941 | F22: 43971 | G22: USD | H22: 1.03 | I22: Regular Cash | J22: =INDEX('CAT - Stock PX'!C:C,MATCH(D22,'CAT - Stock PX'!B:B,0)) -> 116.38
H23: =AVERAGE(H2:H22) -> 1.2014286

Sheet SPX - Tot Ret
A1: Date | B1: Lookup Date | C1: Last Px | D1: Px_Change(%) | F1: Date | G1: Close Price | H1: Dividends | I1: Prc Appr | J1: Total Return | K1: Period Appr | L1: Period Return
A2: 45747 | B2: =_xlfn.CONCAT(MONTH(A2),"-",YEAR(A2)) -> 3-2025 | C2: 5611.85 | D2: =(C2-C3)/C2 -> -0.061058296 | F2: 45747 | G2: 5611.85 | H2: 7.22311 | I2: 0.737 | J2: 0.88426 | K2: -0.057545 | L2: -0.056344
A3: 45716 | B3: =_xlfn.CONCAT(MONTH(A3),"-",YEAR(A3)) -> 2-2025 | C3: 5954.5 | D3: =(C3-C4)/C3 -> -0.014447897 | F3: 45716 | G3: 5954.5 | H3: 7.33114 | I3: 0.84305 | J3: 0.99677 | K3: -0.014242 | L3: -0.01305
A4: 45688 | B4: =_xlfn.CONCAT(MONTH(A4),"-",YEAR(A4)) -> 1-2025 | C4: 6040.53 | D4: =(C4-C5)/C4 -> 0.026305639 | F4: 45688 | G4: 6040.53 | H4: 4.50734 | I4: 0.86968 | J4: 1.02317 | K4: 0.027016 | L4: 0.027793
A5: 45657 | B5: =_xlfn.CONCAT(MONTH(A5),"-",YEAR(A5)) -> 12-2024 | C5: 5881.63 | D5: =(C5-C6)/C5 -> -0.02563065 | F5: 45657 | G5: 5881.63 | H5: 6.66411 | I5: 0.8205 | J5: 0.96846 | K5: -0.02499 | L5: -0.023912
A6: 45625 | B6: =_xlfn.CONCAT(MONTH(A6),"-",YEAR(A6)) -> 11-2024 | C6: 6032.38 | D6: =(C6-C7)/C6 -> 0.054195856 | F6: 45625 | G6: 6032.38 | H6: 7.85278 | I6: 0.86716 | J6: 1.01668 | K6: 0.057301 | L6: 0.0587
A7: 45596 | B7: =_xlfn.CONCAT(MONTH(A7),"-",YEAR(A7)) -> 10-2024 | C7: 5705.45 | D7: =(C7-C8)/C7 -> -0.0099957059 | F7: 45596 | G7: 5705.45 | H7: 4.33677 | I7: 0.76597 | J7: 0.90487 | K7: -0.009897 | L7: -0.009153
A8: 45565 | B8: =_xlfn.CONCAT(MONTH(A8),"-",YEAR(A8)) -> 9-2024 | C8: 5762.48 | D8: =(C8-C9)/C8 -> 0.019797032 | F8: 45565 | G8: 5762.48 | H8: 6.34324 | I8: 0.78362 | J8: 0.92246 | K8: 0.020197 | L8: 0.021354
A9: 45534 | B9: =_xlfn.CONCAT(MONTH(A9),"-",YEAR(A9)) -> 8-2024 | C9: 5648.4 | D9: =(C9-C10)/C9 -> 0.022324906 | F9: 45534 | G9: 5648.4 | H9: 7.6528 | I9: 0.74831 | J9: 0.88227 | K9: 0.022835 | L9: 0.024258
A10: 45504 | B10: =_xlfn.CONCAT(MONTH(A10),"-",YEAR(A10)) -> 7-2024 | C10: 5522.3 | D10: =(C10-C11)/C10 -> 0.011194611 | F10: 45504 | G10: 5522.3 | H10: 4.67544 | I10: 0.70928 | J10: 0.83769 | K10: 0.011321 | L10: 0.012173
A11: 45471 | B11: =_xlfn.CONCAT(MONTH(A11),"-",YEAR(A11)) -> 6-2024 | C11: 5460.48 | D11: =(C11-C12)/C11 -> 0.033508043 | F11: 45471 | G11: 5460.48 | H11: 6.30835 | I11: 0.69014 | J11: 0.81559 | K11: 0.03467 | L11: 0.035879
A12: 45443 | B12: =_xlfn.CONCAT(MONTH(A12),"-",YEAR(A12)) -> 5-2024 | C12: 5277.51 | D12: =(C12-C13)/C12 -> 0.045820851 | F12: 45443 | G12: 5277.51 | H12: 7.83645 | I12: 0.63351 | J12: 0.75271 | K12: 0.048021 | L12: 0.049586
A13: 45412 | B13: =_xlfn.CONCAT(MONTH(A13),"-",YEAR(A13)) -> 4-2024 | C13: 5035.69 | D13: =(C13-C14)/C13 -> -0.043422053 | F13: 45412 | G13: 5035.69 | H13: 4.12459 | I13: 0.55866 | J13: 0.6699 | K13: -0.041615 | L13: -0.040844
... A27: 44985 | B27: =_xlfn.CONCAT(MONTH(A27),"-",YEAR(A27)) -> 2-2023 | C27: 3970.15 | D27: =(C27-C28)/C27 -> -0.026812589 | F27: 44985 | G27: 3970.15 | H27: 6.879 | I27: 0.22885 | J27: 0.29318 | K27: -0.026112 | L27: -0.024472
A28: 44957 | B28: =_xlfn.CONCAT(MONTH(A28),"-",YEAR(A28)) -> 1-2023 | C28: 4076.6 | D28: =(C28-C29)/C28 -> 0.058161213 | F28: AVG | G28: =AVERAGE(G2:G27) -> 5035.5662 | H28: =AVERAGE(H2:H27) -> 6.0869604 | I28: =AVERAGE(I2:I27) -> 0.55862269 | J28: =AVERAGE(J2:J27) -> 0.66853154 | K28: =AVERAGE(K2:K27) -> 0.013024308 | L28: =AVERAGE(L2:L27) -> 0.014276731
A29: 44925 | B29: =_xlfn.CONCAT(MONTH(A29),"-",YEAR(A29)) -> 12-2022 | C29: 3839.5 | D29: =(C29-C30)/C29 -> -0.062667014 | F29: STD | G29: =_xlfn.STDEV.P(G2:G27) -> 669.81903 | H29: =_xlfn.STDEV.P(H2:H27) -> 1.5256997 | I29: =_xlfn.STDEV.P(I2:I27) -> 0.20732433 | J29: =_xlfn.STDEV.P(J2:J27) -> 0.23609453 | K29: =_xlfn.STDEV.P(K2:K27) -> 0.036372436 | L29: =_xlfn.STDEV.P(L2:L27) -> 0.036512643
A30: 44895 | B30: =_xlfn.CONCAT(MONTH(A30),"-",YEAR(A30)) -> 11-2022 | C30: 4080.11 | D30: =(C30-C31)/C30 -> 0.05101088
A31: 44865 | B31: =_xlfn.CONCAT(MONTH(A31),"-",YEAR(A31)) -> 10-2022 | C31: 3871.98 | D31: =(C31-C32)/C31 -> 0.073956994
A32: 44834 | B32: =_xlfn.CONCAT(MONTH(A32),"-",YEAR(A32)) -> 9-2022 | C32: 3585.62 | D32: =(C32-C33)/C32 -> -0.10301705
A33: 44804 | B33: =_xlfn.CONCAT(MONTH(A33),"-",YEAR(A33)) -> 8-2022 | C33: 3955 | D33: =(C33-C34)/C33 -> -0.044321113
A34: 44771 | B34: =_xlfn.CONCAT(MONTH(A34),"-",YEAR(A34)) -> 7-2022 | C34: 4130.29 | D34: =(C34-C35)/C34 -> 0.083507453
A35: 44742 | B35: =_xlfn.CONCAT(MONTH(A35),"-",YEAR(A35)) -> 6-2022 | C35: 3785.38 | D35: =(C35-C36)/C35 -> -0.091607712
A36: 44712 | B36: =_xlfn.CONCAT(MONTH(A36),"-",YEAR(A36)) -> 5-2022 | C36: 4132.15 | D36: =(C36-C37)/C36 -> 5.3241049e-05
A37: 44680 | B37: =_xlfn.CONCAT(MONTH(A37),"-",YEAR(A37)) -> 4-2022 | C37: 4131.93 | D37: =(C37-C38)/C37 -> -0.096439194
A38: 44651 | B38: =_xlfn.CONCAT(MONTH(A38),"-",YEAR(A38)) -> 3-2022 | C38: 4530.41 | D38: =(C38-C39)/C38 -> 0.034537713
A39: 44620 | B39: =_xlfn.CONCAT(MONTH(A39),"-",YEAR(A39)) -> 2-2022 | C39: 4373.94 | D39: =(C39-C40)/C39 -> -0.032375844
A40: 44592 | B40: =_xlfn.CONCAT(MONTH(A40),"-",YEAR(A40)) -> 1-2022 | C40: 4515.55 | D40: =(C40-C41)/C40 -> -0.055503759
A41: 44561 | B41: =_xlfn.CONCAT(MONTH(A41),"-",YEAR(A41)) -> 12-2021 | C41: 4766.18 | D41: =(C41-C42)/C41 -> 0.041790281
... A63: 43951 | B63: =_xlfn.CONCAT(MONTH(A63),"-",YEAR(A63)) -> 4-2020 | C63: 2912.43 | D63: =(C63-C64)/C63 -> 0.1125658
A64: 43921 | B64: =_xlfn.CONCAT(MONTH(A64),"-",YEAR(A64)) -> 3-2020 | C64: 2584.59
A65: AVG | C65: =AVERAGE(C2:C64) -> 4336.4922 | D65: =AVERAGE(D2:D63) -> 0.011091016
A66: SD | C66: =_xlfn.STDEV.P(C2:C64) -> 850.06792 | D66: =_xlfn.STDEV.P(D2:D63) -> 0.051744635

Sheet 10YR Treasury
A1: Security | B1: USGG10YR Index
A2: Start Date | B2: 43585
A3: End Date | B3: 45747
A4: Period | B4: M
A6: Date | B6: Lookup Date | C6: PX_LAST | D6: CHG_PCT_1D | E6: PX_Last (%)
A7: 45747 | B7: =_xlfn.CONCAT(MONTH(A7),"-",YEAR(A7)) -> 3-2025 | C7: 4.2053 | D7: -0.071 | E7: =C7/(100*12) -> 0.0035044167
A8: 45716 | B8: =_xlfn.CONCAT(MONTH(A8),"-",YEAR(A8)) -> 2-2025 | C8: 4.2082 | D8: -7.2813 | E8: =C8/(100*12) -> 0.0035068333
A9: 45688 | B9: =_xlfn.CONCAT(MONTH(A9),"-",YEAR(A9)) -> 1-2025 | C9: 4.5387 | D9: -0.6623 | E9: =C9/(100*12) -> 0.00378225
A10: 45657 | B10: =_xlfn.CONCAT(MONTH(A10),"-",YEAR(A10)) -> 12-2024 | C10: 4.569 | D10: 9.6062 | E10: =C10/(100*12) -> 0.0038075
A11: 45625 | B11: =_xlfn.CONCAT(MONTH(A11),"-",YEAR(A11)) -> 11-2024 | C11: 4.1685 | D11: -2.7036 | E11: =C11/(100*12) -> 0.00347375
A12: 45596 | B12: =_xlfn.CONCAT(MONTH(A12),"-",YEAR(A12)) -> 10-2024 | C12: 4.2844 | D12: 13.3152 | E12: =C12/(100*12) -> 0.0035703333
A13: 45565 | B13: =_xlfn.CONCAT(MONTH(A13),"-",YEAR(A13)) -> 9-2024 | C13: 3.7809 | D13: -3.1386 | E13: =C13/(100*12) -> 0.00315075
A14: 45534 | B14: =_xlfn.CONCAT(MONTH(A14),"-",YEAR(A14)) -> 8-2024 | C14: 3.9034 | D14: -3.131 | E14: =C14/(100*12) -> 0.0032528333
A15: 45504 | B15: =_xlfn.CONCAT(MONTH(A15),"-",YEAR(A15)) -> 7-2024 | C15: 4.0296 | D15: -8.3363 | E15: =C15/(100*12) -> 0.003358
A16: 45471 | B16: =_xlfn.CONCAT(MONTH(A16),"-",YEAR(A16)) -> 6-2024 | C16: 4.3961 | D16: -2.2777 | E16: =C16/(100*12) -> 0.0036634167
A17: 45443 | B17: =_xlfn.CONCAT(MONTH(A17),"-",YEAR(A17)) -> 5-2024 | C17: 4.4985 | D17: -3.8738 | E17: =C17/(100*12) -> 0.00374875
A18: 45412 | B18: =_xlfn.CONCAT(MONTH(A18),"-",YEAR(A18)) -> 4-2024 | C18: 4.6798 | D18: 11.4161 | E18: =C18/(100*12) -> 0.0038998333
... A68: 43889 | B68: =_xlfn.CONCAT(MONTH(A68),"-",YEAR(A68)) -> 2-2020 | C68: 1.1486 | D68: -23.7723 | E68: =C68/(100*12) -> 0.00095716667
B69: AVG | C69: =AVERAGE(C7:C68) -> 2.7880048 | D69: =AVERAGE(D7:D68) -> 2.6047597 | E69: =AVERAGE(E7:E68) -> 0.0023233374
B70: STD | C70: =_xlfn.STDEV.P(C7:C68) -> 1.4259782 | D70: =_xlfn.STDEV.P(D7:D68) -> 13.550138 | E70: =_xlfn.STDEV.P(E7:E68) -> 0.0011883152

Sheet EBAY Income Statement
A1: eBay Inc. (EBAY) | N1: Rev growth | O1: 0.075
A2: $67.05
B3: 31 DEC '19 | C3: 31 DEC '20 | D3: 31 DEC '21 | E3: 31 DEC '22 | F3: 31 DEC '23 | G3: 31 DEC '24
B4: RECAP | C4: RECAP | D4: RECAP | E4: RECAP | F4: RECAP
A5: Net revenues | B5: 7429 | C5: 8894 | D5: 10420 | E5: 9795 | F5: 10112 | G5: 10283 | H5: 11054.225 | I5: 11883.292 | J5: 12774.539 | K5: 13732.629 | L5: 14762.576
A6: Cost of net revenues | B6: -1585 | C6: -1797 | D6: -2650 | E6: -2680 | F6: -2833 | G6: -2880
A7: Gross profit | B7: 5844 | C7: 7097 | D7: 7770 | E7: 7115 | F7: 7279 | G7: 7403
A8: Total operating expenses | B8: -4074 | C8: -4461 | D8: -4847 | E8: -4765 | F8: -5338 | G8: -5085
A9: Sales and marketing | B9: -1866 | C9: -2091 | D9: -2170 | E9: -2136 | F9: -2217 | G9: -2319
A10: Product development | B10: -930 | C10: -1028 | D10: -1325 | E10: -1330 | F10: -1544 | G10: -1479
A11: General and administrative | B11: -988 | C11: -985 | D11: -921 | E11: -963 | F11: -1196 | G11: -914
A12: Provision for transaction losses | B12: -262 | C12: -330 | D12: -422 | E12: -332 | F12: -360 | G12: -353
A13: Amortization of acquired intangible assets | B13: -28 | C13: -27 | D13: -9 | E13: -4 | F13: -21 | G13: -20 | H13: =H5*H14 -> -22.290036 | I13: =I5*I14 -> -23.961789 | J13: =J5*J14 -> -25.758923 | K13: =K5*K14 -> -27.690842 | L13: =L5*L14 -> -29.767656
A14: as % of sales | B14: =B13/B5 -> -0.0037690133 | C14: =C13/C5 -> -0.0030357544 | D14: =D13/D5 -> -0.00086372361 | E14: =E13/E5 -> -0.00040837162 | F14: =F13/F5 -> -0.0020767405 | G14: =G13/G5 -> -0.0019449577 | H14: =AVERAGE(B14:G14) -> -0.0020164269 | I14: =H14 -> -0.0020164269 | J14: =I14 -> -0.0020164269 | K14: =J14 -> -0.0020164269 | L14: =K14 -> -0.0020164269
A15: Income from operations | B15: 1770 | C15: 2636 | D15: 2923 | E15: 2350 | F15: 1941 | G15: 2318
A16: Interest and other, net | B16: -118 | C16: 709 | D16: -2525 | E16: -3951 | F16: 1766 | G16: -40
A17: Gain / loss on equity investments and warrant, net | B17: 133 | C17: 1007 | D17: -2365 | E17: -3786 | F17: 1832 | G17: -76
A18: Interest and other income / expense, net | B18: -251 | C18: -298 | D18: -160 | E18: -165 | F18: -66 | G18: 36 | H18: =H5*$H$19 -> -188.87735 | I18: =I5*$H$19 -> -203.04315 | J18: =J5*$H$19 -> -218.27138 | K18: =K5*$H$19 -> -234.64174 | L18: =L5*$H$19 -> -252.23987
B19: =B18/B5 -> -0.033786512 | C19: =C18/C5 -> -0.033505734 | D19: =D18/D5 -> -0.015355086 | E19: =E18/E5 -> -0.016845329 | F19: =F18/F5 -> -0.0065268987 | G19: =G18/G5 -> 0.0035009239 | H19: =AVERAGE(B19:G19) -> -0.01708644
A20: Interest expense | D20: -269 | E20: -235 | F20: -263 | G20: -259
A21: Interest and other income, net excluding interest expense | D21: 109 | E21: 70 | F21: 197 | G21: 295
A22: Gain / loss on divested business
A23: Income from continuing operations before income taxes | B23: 1652 | C23: 3345 | D23: 398 | E23: -1601 | F23: 3707 | G23: 2278
A24: Provision for income taxes | B24: -219 | C24: -858 | D24: -146 | E24: 327 | F24: -932 | G24: -297
A25: Tax Rate | B25: =B24/B23 -> -0.13256659 | C25: =C24/C23 -> -0.25650224 | D25: =D24/D23 -> -0.36683417 | E25: =E24/E23 -> -0.20424735 | F25: =F24/F23 -> -0.25141624 | G25: =G24/G23 -> -0.13037752
A26: Income / loss from continuing operations | B26: 1433 | C26: 2487 | D26: 252 | E26: -1274 | F26: 2775 | G26: 1981
A27: Minority interests
A28: Income / loss from discontinued operations, net of income taxes | B28: 353 | C28: 3180 | D28: 13356 | E28: 5 | F28: -8 | G28: -6
A29: Net income / loss | B29: 1786 | C29: 5667 | D29: 13608 | E29: -1269 | F29: 2767 | G29: 1975
A30: Per share
A31: Basic | B31: 2.1 | C31: 7.98 | D31: 20.87 | E31: -2.27 | F31: 5.22 | G31: 3.99
A32: Continuing operations | B32: 1.69 | C32: 3.5 | D32: 0.39 | E32: -2.28 | F32: 5.24 | G32: 4
A33: Discontinued operations | B33: 0.41 | C33: 4.48 | D33: 20.48 | E33: 0.01 | F33: -0.02 | G33: -0.01
A34: Diluted | B34: 2.09 | C34: 7.89 | D34: 20.54 | E34: -2.27 | F34: 5.19 | G34: 3.94
A35: Continuing operations | B35: 1.68 | C35: 3.46 | D35: 0.38 | E35: -2.28 | F35: 5.21 | G35: 3.95
A36: Discontinued operations | B36: 0.41 | C36: 4.43 | D36: 20.16 | E36: 0.01 | F36: -0.02 | G36: -0.01
A37: Weighted average shares
A38: Basic | B38: 849 | C38: 710 | D38: 652 | E38: 558 | F38: 530 | G38: 496
A39: Diluted | B39: 856 | C39: 718 | D39: 663 | E39: 558 | F39: 533 | G39: 501
A40: All figures in millions of U.S. Dollar except per share items.

Sheet EBAY Balance Sheet
A1: eBay Inc. (EBAY)
A2: $67.05
B3: 31 DEC '19 | C3: 31 DEC '20 | D3: 31 DEC '21 | E3: 31 DEC '22 | F3: 31 DEC '23 | G3: 31 DEC '24 | P3: 2024 | Q3: 2025 | R3: 2026 | S3: 2027 | T3: 2028 | U3: 2029
B4: RECAP | C4: RECAP | D4: RECAP | E4: RECAP | F4: RECAP | N4: Net Working Capital | P4: =G7-G41 -> 1469 | Q4: =H7-H41 -> 4613.849 | R4: =I7-I41 -> 4959.8877 | S4: =J7-J41 -> 5331.8792 | T4: =K7-K41 -> 5731.7702 | U4: =L7-L41 -> 6161.6529
A5: GAAP/IFRS Balance Sheet | N5: Change | Q5: =Q4-P4 -> 3144.849 | R5: =R4-Q4 -> 346.03867 | S5: =S4-R4 -> 371.99157 | T5: =T4-S4 -> 399.89094 | U5: =U4-T4 -> 429.88276
A6: Total assets | B6: 18174 | C6: 19310 | D6: 26626 | E6: 20850 | F6: 21620 | G6: 19365
A7: Total current assets | B7: 4706 | C7: 7190 | D7: 9111 | E7: 9290 | F7: 11016 | G7: 7567 | H7: =$H$8*FCFF!C15 -> 9852.6372 | I7: =$H$8*FCFF!D15 -> 10591.585 | J7: =$H$8*FCFF!E15 -> 11385.954 | K7: =$H$8*FCFF!F15 -> 12239.9 | L7: =$H$8*FCFF!G15 -> 13157.893
B8: =B7/'EBAY Income Statement'!B5 -> 0.63346345 | C8: =C7/'EBAY Income Statement'!C5 -> 0.80841016 | D8: =D7/'EBAY Income Statement'!D5 -> 0.8743762 | E8: =E7/'EBAY Income Statement'!E5 -> 0.94844308 | F8: =F7/'EBAY Income Statement'!F5 -> 1.0893987 | G8: =G7/'EBAY Income Statement'!G5 -> 0.73587474 | H8: =AVERAGE(C8:G8) -> 0.89130059
A9: Cash and cash equivalents | B9: 901 | C9: 1101 | D9: 1379 | E9: 2154 | F9: 1985 | G9: 2433
A10: Short-term investments | B10: 1850 | C10: 2392 | D10: 5944 | E10: 2625 | F10: 2533 | G10: 3457
A11: Equity investment in Adevinta | D11: 0 | E11: 2692 | F11: 4474 | G11: 0
A12: Customer accounts and funds receivable | C12: 290 | D12: 681 | E12: 763 | F12: 1013 | G12: 962
A13: Other current assets | B13: 1619 | C13: 1142 | D13: 1107 | E13: 1056 | F13: 1011 | G13: 715
A14: Accounts receivable, net | B14: 555 | C14: 362
A15: Other current assets excluding accounts receivable, net | B15: 1064 | C15: 780
A16: Current assets held for sale | B16: 195
A17: Current assets of discontinued operations | B17: 141 | C17: 2265
A18: Long-term investments | B18: 1275 | C18: 833 | D18: 2575 | E18: 1797 | F18: 1129 | G18: 2439
A19: Property and equipment, net | B19: 1460 | C19: 1292 | D19: 1236 | E19: 1238 | F19: 1243 | G19: 1263 | H19: =$H$21*FCFF!C15 -> 1533.8658 | I19: =$H$21*FCFF!D15 -> 1648.9058 | J19: =$H$21*FCFF!E15 -> 1772.5737 | K19: =$H$21*FCFF!F15 -> 1905.5167 | L19: =$H$21*FCFF!G15 -> 2048.4305
C20: =C19-B19 -> -168 | D20: =D19-C19 -> -56 | E20: =E19-D19 -> 2 | F20: =F19-E19 -> 5 | G20: =G19-F19 -> 20 | H20: =H19-G19 -> 270.86582 | I20: =I19-H19 -> 115.03994 | J20: =J19-I19 -> 123.66793 | ... L20: =L19-K19 -> 142.91375
B21: =B19/'EBAY Income Statement'!B5 -> 0.19652712 | C21: =C19/'EBAY Income Statement'!C5 -> 0.14526647 | D21: =D19/'EBAY Income Statement'!D5 -> 0.11861804 | E21: =E19/'EBAY Income Statement'!E5 -> 0.12639102 | F21: =F19/'EBAY Income Statement'!F5 -> 0.12292326 | G21: =G19/'EBAY Income Statement'!G5 -> 0.12282408 | H21: =AVERAGE(B21:G21) -> 0.13875833
A22: Property and equipment, net | B22: 1460 | C22: 1292 | D22: 1236 | E22: 1238 | F22: 1243 | G22: 1263 | H22: =$H$21*FCFF!J15 -> 1548.1343 | I22: =$H$21*FCFF!K15 -> 1679.7258 | J22: =$H$21*FCFF!L15 -> 1822.5024 | K22: =$H$21*FCFF!M15 -> 1977.4152 | L22: =$H$21*FCFF!N15 -> 2145.4954
C23: =C22-B22 -> -168 | D23: =D22-C22 -> -56 | E23: =E22-D22 -> 2 | F23: =F22-E22 -> 5 | G23: =G22-F22 -> 20 | H23: =H22-G22 -> 285.13434 | I23: =I22-H22 -> 131.59142 | J23: =J22-I22 -> 142.77669 | ... L23: =L22-K22 -> 168.08029
B24: =B22/'EBAY Income Statement'!B8 -> -0.35837015 | C24: =C22/'EBAY Income Statement'!C8 -> -0.28962116 | D24: =D22/'EBAY Income Statement'!D8 -> -0.25500309 | E24: =E22/'EBAY Income Statement'!E8 -> -0.25981112 | F24: =F22/'EBAY Income Statement'!F8 -> -0.23285875 | G24: =G22/'EBAY Income Statement'!G8 -> -0.24837758 | H24: =AVERAGE(B24:G24) -> -0.27400698
A25: Property and equipment, net | B25: 1460 | C25: 1292 | D25: 1236 | E25: 1238 | F25: 1243 | G25: 1263 | H25: =$H$21*FCFF!Q15 -> 1519.5973 | I25: =$H$21*FCFF!R15 -> 1618.3711 | J25: =$H$21*FCFF!S15 -> 1723.5652 | K25: =$H$21*FCFF!T15 -> 1835.597 | L25: =$H$21*FCFF!U15 -> 1954.9108
C26: =C25-B25 -> -168 | D26: =D25-C25 -> -56 | E26: =E25-D25 -> 2 | F26: =F25-E25 -> 5 | G26: =G25-F25 -> 20 | H26: =H25-G25 -> 256.5973 | I26: =I25-H25 -> 98.773825 | J26: =J25-I25 -> 105.19412 | ... L26: =L25-K25 -> 119.3138
B27: =B25/'EBAY Income Statement'!B11 -> -1.4777328 | C27: =C25/'EBAY Income Statement'!C11 -> -1.3116751 | D27: =D25/'EBAY Income Statement'!D11 -> -1.3420195 | E27: =E25/'EBAY Income Statement'!E11 -> -1.2855659 | F27: =F25/'EBAY Income Statement'!F11 -> -1.0392977 | G27: =G25/'EBAY Income Statement'!G11 -> -1.3818381 | H27: =AVERAGE(B27:G27) -> -1.3063549
A28: Goodwill | B28: 4533 | C28: 4285 | D28: 4178 | E28: 4262 | F28: 4267 | G28: 4269
A29: Operating lease right-of-use assets | B29: 583 | C29: 430 | D29: 289 | E29: 513 | F29: 493 | G29: 427
A30: Deferred tax asset, non-current | B30: 3980 | C30: 3537 | D30: 3255 | E30: 3169 | F30: 3089 | G30: 2936
A31: Long-term assets held for sale | B31: 878 | C31: 549
A32: Long-term assets of discontinued operations | B32: 306
A33: Equity investment in adevinta | C33: 0 | D33: 5391
A34: Other assets | B34: 453 | C34: 1194 | D34: 591 | E34: 581 | F34: 383 | G34: 464
A35: Intangible assets, net | B35: 39 | C35: 12
A36: Other assets excluding intangible assets, net | B36: 414 | C36: 1182
A37: Warrant asset | B37: 281 | C37: 1051
A38: Other assets excluding warrant asset | B38: 133 | C38: 131
A39: Total liabilities and stockholders' equity | B39: 18174 | C39: 19310 | D39: 26626 | E39: 20850 | F39: 21620 | G39: 19365
A40: Total liabilities | B40: 15304 | C40: 15749 | D40: 16848 | E40: 15697 | F40: 15224 | G40: 14207
A41: Total current liabilities | B41: 4066 | C41: 4002 | D41: 4622 | E41: 4271 | F41: 4520 | G41: 6098 | H41: =$H$42*FCFF!C15 -> 5238.7882 | I41: =$H$42*FCFF!D15 -> 5631.6974 | J41: =$H$42*FCFF!E15 -> 6054.0747 | K41: =$H$42*FCFF!F15 -> 6508.1303 | L41: =$H$42*FCFF!G15 -> 6996.24
B42: ='EBAY Balance Sheet'!B41/'EBAY Income Statement'!B5 -> 0.54731458 | C42: ='EBAY Balance Sheet'!C41/'EBAY Income Statement'!C5 -> 0.44996627 | D42: ='EBAY Balance Sheet'!D41/'EBAY Income Statement'!D5 -> 0.44357006 | E42: ='EBAY Balance Sheet'!E41/'EBAY Income Statement'!E5 -> 0.4360388 | F42: ='EBAY Balance Sheet'!F41/'EBAY Income Statement'!F5 -> 0.44699367 | G42: ='EBAY Balance Sheet'!G41/'EBAY Income Statement'!G5 -> 0.5930176 | H42: =AVERAGE(C42:G42) -> 0.47391728
A43: Short-term debt | B43: 1020 | C43: 6 | D43: 1355 | E43: 1150 | F43: 750 | G43: 1673
A44: Accounts payable | B44: 229 | C44: 278 | D44: 262 | E44: 261 | F44: 267 | G44: 257
A45: Funds payable and amounts due to customers
A46: Accrued expenses and other current liabilities | B46: 2097 | C46: 2146 | D46: 2634 | E46: 2634 | F46: 3250 | G46: 3202
A47: Borrowings from credit agreement
A48: Customer accounts and funds payable | C48: 379 | D48: 707 | E48: 768 | F48: 1054 | G48: 1018
A49: Accrued expenses and other current liabilities excluding borrowings from credit agreement and customer accounts and funds payable | C49: 1767 | D49: 1927 | E49: 1866 | F49: 2196 | G49: 2184
A50: Deferred revenue | B50: 129 | C50: 98
A51: Income taxes payable | B51: 169 | C51: 167 | D51: 371 | E51: 226 | F51: 253 | G51: 966
A52: Current liabilities held for sale | B52: 163
A53: Current liabilities of discontinued operations | B53: 259 | C53: 1307
A54: Operating lease liabilities | B54: 461 | C54: 316 | D54: 200 | E54: 418 | F54: 387 | G54: 320
A55: Deferred and other tax liabilities, net | B55: 2355 | C55: 2368 | D55: 3116 | E55: 2245 | F55: 2408 | G55: 1405
A56: Long-term debt | B56: 6738 | C56: 7740 | D56: 7727 | E56: 7721 | F56: 6973 | G56: 5752
A57: Other liabilities | B57: 1353 | C57: 1260 | D57: 1183 | E57: 1042 | F57: 936 | G57: 632
A58: Long-term liabilities held for sale | B58: 305 | C58: 63
A59: Long-term liabilities of discontinued operations | B59: 26
A60: Total stockholders' equity | B60: 2870 | C60: 3561 | D60: 9778 | E60: 5153 | F60: 6396 | G60: 5158
A61: Common stock | B61: 2 | C61: 2 | D61: 2 | E61: 2 | F61: 2 | G61: 2
A62: Additional paid-in capital | B62: 16126 | C62: 16497 | D62: 16659 | E62: 17279 | F62: 17792 | G62: 18289
A63: Unearned stock-based compensation
A64: Treasury stock | B64: -31396 | C64: -36515 | D64: -43371 | E64: -46702 | F64: -48114 | G64: -51290
A65: Retained earnings | B65: 17754 | C65: 22961 | D65: 36090 | E65: 34315 | F65: 36531 | G65: 37951
A66: Accumulated other comprehensive income | B66: 384 | C66: 616 | D66: 398 | E66: 259 | F66: 185 | G66: 206
A67: Growth
A68: Total assets | B68: -20.355844 | C68: 6.250688 | D68: 37.887104 | E68: -21.693083 | F68: 3.693046 | G68: -10.430158
A69: Total current assets | B69: -33.960144 | C69: 52.78368 | D69: 26.717663 | E69: 1.964658 | F69: 18.579117 | G69: -31.309006
A70: Cash and cash equivalents | B70: -59.082653 | C70: 22.197557 | D70: 25.249773 | E70: 56.200146 | F70: -7.845868 | G70: 22.56927
A71: Short-term investments | B71: -31.809805 | C71: 29.297297 | D71: 148.49498 | E71: -55.83782 | F71: -3.504762 | G71: 36.478485
A72: Equity investment in Adevinta | B72: - | C72: - | D72: - | E72: - | F72: 66.19614 | G72: -100
A73: Loans and interest receivable, net | B73: - | C73: - | D73: - | E73: - | F73: - | G73: -
A74: Funds receivable customer accounts | B74: - | C74: - | D74: - | E74: - | F74: - | G74: -
A75: Customer accounts and funds receivable | B75: - | C75: - | D75: 134.82759 | E75: 12.041116 | F75: 32.7654 | G75: -5.034551
A76: Other current assets | B76: -26.775215 | C76: -29.462631 | D76: -3.064799 | E76: -4.607046 | F76: -4.261363 | G76: -29.277943
A77: Accounts receivable, net | B77: -22.050562 | C77: -34.774776 | D77: - | E77: - | F77: - | G77: -
A78: Other current assets excluding accounts receivable, net | B78: -29.019346 | C78: -26.691729 | D78: - | E78: - | F78: - | G78: -
A79: Current assets held for sale | B79: - | C79: - | D79: - | E79: - | F79: - | G79: -
A80: Current assets of discontinued operations | B80: - | C80: 1506.3829 | D80: - | E80: - | F80: - | G80: -
A81: Long-term investments | B81: -66.25198 | C81: -34.666668 | D81: 209.12364 | E81: -30.213593 | F81: -37.173065 | G81: 116.03188
A82: Property and equipment, net | B82: -8.578585 | C82: -11.506849 | D82: -4.334365 | E82: 0.161812 | F82: 0.403877 | G82: 1.60901
A83: Goodwill | B83: -12.151163 | C83: -5.470991 | D83: -2.497083 | E83: 2.010531 | F83: 0.117316 | G83: 0.046871
A84: Operating lease right-of-use assets | B84: - | C84: -26.243568 | D84: -32.7907 | E84: 77.50865 | F84: -3.898635 | G84: -13.387424
A85: Deferred tax asset, non-current | B85: -16.944908 | C85: -11.130653 | D85: -7.972858 | E85: -2.642089 | F85: -2.524456 | G85: -4.953059
A86: Long-term assets held for sale | B86: - | C86: -37.471527 | D86: - | E86: - | F86: - | G86: -
A87: Long-term assets of discontinued operations | B87: - | C87: - | D87: - | E87: - | F87: - | G87: -
A88: Equity investment in adevinta | B88: - | C88: - | D88: - | E88: - | F88: - | G88: -
A89: Other assets | B89: 23.770493 | C89: 163.57616 | D89: -50.502514 | E89: -1.692047 | F89: -34.079174 | G89: 21.148825
A90: Intangible assets, net | B90: -57.608696 | C90: -69.23077 | D90: - | E90: - | F90: - | G90: -
A91: Other assets excluding intangible assets, net | B91: 51.09489 | C91: 185.50725 | D91: - | E91: - | F91: - | G91: -
A92: Warrant asset | B92: - | C92: 274.02136 | D92: - | E92: - | F92: - | G92: -
A93: Other assets excluding warrant asset | B93: - | C93: -1.503759 | D93: - | E93: - | F93: - | G93: -
A94: Total liabilities and stockholders' equity | B94: -20.355844 | C94: 6.250688 | D94: 37.887104 | E94: -21.693083 | F94: 3.693046 | G94: -10.430158
A95: Total liabilities | B95: -7.461604 | C95: 2.907736 | D95: 6.978221 | E95: -6.831671 | F95: -3.013315 | G95: -6.680242
A96: Total current liabilities | B96: -8.71127 | C96: -1.574029 | D96: 15.492254 | E96: -7.594115 | F96: 5.830017 | G96: 34.911503
A97: Short-term debt | B97: -34.023285 | C97: -99.411766 | D97: 22483.334 | E97: -15.129151 | F97: -34.782608 | G97: 123.06667
A98: Accounts payable | B98: -19.93007 | C98: 21.39738 | D98: -5.755396 | E98: -0.381679 | F98: 2.29885 | G98: -3.745318
A99: Funds payable and amounts due to customers | B99: - | C99: - | D99: - | E99: - | F99: - | G99: -
A100: Accrued expenses and other current liabilities | B100: -10.192719 | C100: 2.336671 | D100: 22.73998 | E100: 0 | F100: 23.386484 | G100: -1.476923
...

Sheet EBAY Cash Flows
A1: eBay Inc. (EBAY)
A2: $67.05
B3: 31 DEC '19 | C3: 31 DEC '20 | D3: 31 DEC '21 | E3: 31 DEC '22 | F3: 31 DEC '23 | G3: 31 DEC '24
B4: RECAP | C4: RECAP | D4: RECAP | E4: RECAP | F4: RECAP
A5: Net cash provided by operating activities | B5: 3114 | C5: 2419 | D5: 2657 | E5: 2254 | F5: 2426 | G5: 2414
A6: Net income / loss | B6: 1786 | C6: 5667 | D6: 13608 | E6: -1269 | F6: 2767 | G6: 1975
A7: Income / loss from discontinued operations, net of income taxes | B7: -353 | C7: -3180 | D7: -13356 | E7: -5 | F7: 8 | G7: 6
A8: Adjustments | B8: 983 | C8: 517 | D8: 2841 | E8: 3901 | F8: -344 | G8: 433
A9: Provision for transaction losses | B9: 262 | C9: 330 | D9: 422 | E9: 332 | F9: 360 | G9: 353
A10: Depreciation and amortization | B10: 600 | C10: 583 | D10: 502 | E10: 442 | F10: 403 | G10: 324
A11: Stock-based compensation | B11: 415 | C11: 417 | D11: 477 | E11: 494 | F11: 575 | G11: 588
A12: Loss / gain on sale of investments and other, net | B12: 0 | C12: 2 | D12: -159 | E12: 21 | F12: -5 | G12: 8
A13: Gain on sale of business | B13: 52
A14: Deferred income taxes | B14: 7 | C14: 414 | D14: -680 | E14: -780 | F14: 255 | G14: -874
A15: Change in fair value of warrant | B15: -133 | C15: -770 | D15: -354 | E15: 230 | F15: -150 | G15: -158
A16: Change in fair value of equity investment in Adevinta | B16: 0 | C16: 0 | D16: 3070 | E16: 2691 | F16: -1782 | G16: 156
A17: Loss on impairment of equity investment in Paytm Mall | B17: 0 | C17: 0 | D17: 160
A18: Change in fair value of equity investment in Adyen | B18: 0 | C18: -239 | D18: -476 | E18: 554 | F18: -2 | G18: 57
A19: Gain on equity investment in KakaoBank | B19: 0 | C19: -239 | D19: -486 | E19: 293 | F19: -2 | G19: 0
A20: Change in fair value of equity investment in Adyen excluding gain on equity investment in KaKaobank | C20: 0 | D20: 10 | E20: 261 | F20: 0 | G20: 57
A21: Change in fair value of equity investment in Gmarket | C21: 0 | D21: 3 | E21: 294 | F21: 96 | G21: 13
A22: Gain / loss on divestiture of businesses | B22: 0 | C22: 0 | D22: 10
A23: Changes in assets and liabilities, net of acquisition effects | B23: -220 | C23: -220 | D23: -134 | E23: -377 | F23: -94 | G23: -34
A24: Accounts receivable | B24: -93
A25: Other current assets | B25: 91 | C25: -646 | D25: 236 | E25: -33 | F25: -319 | G25: 67
A26: Other non-current assets | B26: 190 | C26: 141 | D26: 188 | E26: 20 | F26: 474 | G26: 37
A27: Accounts payable | B27: -11 | C27: 69 | D27: 9 | E27: 6 | F27: 15 | G27: -8
A28: Accrued expenses and other liabilities | B28: -306 | C28: 189 | D28: -552 | E28: -410 | F28: -212 | G28: -644
A29: Deferred revenue | B29: -1
A30: Income taxes payable and other tax liabilities | B30: -90 | C30: 27 | D30: -15 | E30: 40 | F30: -52 | G30: 514
A31: Net cash provided by continuing operating activities | B31: 2416 | C31: 3004 | D31: 3093 | E31: 2627 | F31: 2431 | G31: 2414
A32: Net cash provided by / used in discontinued operating activities | B32: 698 | C32: -585 | D32: -436 | E32: -373 | F32: -5 | G32: 0
A33: Net cash provided by / used in investing activities | B33: 2787 | C33: 3794 | D33: 3663 | E33: 2461 | F33: 240 | G33: 2213
A34: Purchases of property and equipment | B34: -508 | C34: -463 | D34: -444 | E34: -449 | F34: -456 | G34: -458
A35: Purchases of investments | B35: -46966 | C35: -32887 | D35: -22161 | E35: -18534 | F35: -13874 | G35: -13855
A36: Maturities and sales of investments | B36: 50548 | C36: 33129 | D36: 18770 | E36: 20626 | F36: 14502 | G36: 13342
A37: Maturities and sales of investments excluding Proceeds from the sale of shares in KakaoBank | C37: 33129 | D37: 18770 | E37: 20626 | F37: 14502 | G37: 12306
A38: Proceeds from the sale of shares in KakaoBank | E38: 0 | F38: 0 | G38: 1036
A39: Settlement of foreign exchange derivative instruments for equity investments | B39: 0 | C39: 0 | D39: 85
A40: Exercise of options under warrant | B40: 0 | C40: 0 | D40: -110 | E40: 0 | F40: 0 | G40: -108
A41: Equity investment in Flipkart | B41: -160
A42: Acquisition of TCGplayer, net of cash acquired | C42: 0 | D42: 0 | E42: -208 | F42: 0 | G42: 0
A43: Other | B43: -14 | C43: 42 | D43: 4 | E43: -71 | F43: -38 | G43: -13
A44: Proceeds from sale of shares in Adevinta | B44: 0 | C44: 0 | D44: 2325 | E44: 8 | F44: 0 | G44: 2410
A45: Proceeds from the sale of shares in Adyen | C45: 0 | D45: 0 | E45: 800 | F45: 0 | G45: 573
A46: Proceeds from sale of shares in Gmarket, net | E46: 0 | F46: 0 | G46: 322
A47: Proceeds from sale of shares in Adevinta | C47: 0 | D47: 114 | E47: 287 | F47: 106 | G47: 0
A48: Net cash provided by / used in continuing investing activities | B48: 2900 | C48: -179 | D48: -1417 | E48: 2459 | F48: 240 | G48: 2213
A49: Net cash provided by / used in discontinued investing activities | B49: -113 | C49: 3973 | D49: 5080 | E49: 2 | F49: 0 | G49: 0
A50: Net cash used in / provided by financing activities | B50: -7091 | C50: -5692 | D50: -6532 | E50: -3792 | F50: -2450 | G50: -3806
A51: Proceeds from issuance of common stock | B51: 106 | C51: 90 | D51: 93 | E51: 87 | F51: 83 | G51: 92
A52: Repurchases of common stock | B52: -4973 | C52: -5137 | D52: -7055 | E52: -3143 | F52: -1401 | G52: -3149
A53: Tax withholdings related to net share settlements of restricted stock units and awards | B53: -202 | C53: -175 | D53: -236 | E53: -160 | F53: -171 | G53: -188
A54: Payments for dividends | B54: -473 | C54: -447 | D54: -466 | E54: -489 | F54: -528 | G54: -533
A55: Proceeds from issuance of long-term debt, net | B55: 0 | C55: 1765 | D55: 2478 | E55: 1143 | F55: 0 | G55: 0 | H55: =$H$56*FCFE!C18 -> 1018.7435 | I55: =$H$56*FCFE!D18 -> 1095.1493 | J55: =$H$56*FCFE!E18 -> 1177.2855 | K55: =$H$56*FCFE!F18 -> 1265.5819 | L55: =$H$56*FCFE!G18 -> 1360.5005
B56: =B55/'EBAY Income Statement'!B5 -> 0 | C56: =C55/'EBAY Income Statement'!C5 -> 0.19844839 | D56: =D55/'EBAY Income Statement'!D5 -> 0.2378119 | E56: =E55/'EBAY Income Statement'!E5 -> 0.11669219 | F56: =F55/'EBAY Income Statement'!F5 -> 0 | G56: =G55/'EBAY Income Statement'!G5 -> 0 | H56: =AVERAGE(B56:G56) -> 0.092158747
A57: Repayment of debt | B57: -1550 | C57: -1771 | D57: -1156 | E57: -1355 | F57: -1150 | G57: -750 | H57: =$H$58*FCFE!C18 -> -1554.4145 | I57: =$H$58*FCFE!D18 -> -1670.9956 | J57: =$H$58*FCFE!E18 -> -1796.3203 | K57: =$H$58*FCFE!F18 -> -1931.0443 | L57: =$H$58*FCFE!G18 -> -2075.8726
B58: =B57/'EBAY Income Statement'!B5 -> -0.20864181 | C58: =C57/'EBAY Income Statement'!C5 -> -0.199123 | D58: =D57/'EBAY Income Statement'!D5 -> -0.1109405 | E58: =E57/'EBAY Income Statement'!E5 -> -0.13833589 | F58: =F57/'EBAY Income Statement'!F5 -> -0.11372627 | G58: =G57/'EBAY Income Statement'!G5 -> -0.072935914 | H58: =AVERAGE(B58:G58) -> -0.14061723
A59: Borrowings under commercial paper program | E59: 0 | F59: 0 | G59: 441
A60: Net funds receivable and payable activity | B60: 0 | C60: 0 | D60: -208 | E60: 125 | F60: 717 | G60: 305
A61: Other | B61: 5 | C61: -5 | D61: -7 | E61: 0 | F61: 0 | G61: -24
A62: Net cash provided by / used in continuing financing activities | B62: -7087 | C62: -5680 | D62: -6557 | E62: -3792 | F62: -2450 | G62: -3806
A63: Net cash provided by / used in discontinued financing activities | B63: -4 | C63: -12 | D63: 25
A64: Effect of exchange rate changes on cash and cash equivalents | B64: -33 | C64: 77 | D64: 24 | E64: -57 | F64: 5 | G64: -28
A65: Net decrease / increase in cash and cash equivalents before net decrease / increase in cash and cash equivalents - continuing | B65: -1223 | C65: 598 | D65: -188 | E65: 866 | F65: 221 | G65: 793
A66: Net increase / decrease in cash, cash equivalents and restricted cash | B66: -1223 | C66: 598 | D66: -188 | E66: 866 | F66: 221 | G66: 793
A67: Cash and cash equivalents at beginning of period | B67: 2219 | C67: 996 | D67: 1594 | E67: 1406 | F67: 2272 | G67: 2493
A68: Cash and cash equivalents at end of period | B68: 996 | C68: 1594 | D68: 1406 | E68: 2272 | F68: 2493 | G68: 3286
A69: Interest | B69: -304 | C69: 271 | D69: -253 | E69: -244 | F69: -275 | G69: -264
A70: Income taxes | B70: -249 | C70: 493 | D70: -929 | E70: -540 | F70: -746 | G70: -722
A71: Non-cash investing activities
A72: Common stock issued for acquisition
A73: Note receivable from divested business
A74: Relinquishment of equity method investment
A75: Sale of business in exchange for ownership interest in Flipkart
A76: Common stock options assumed pursuant to acquisition
A77: Equity investment in Adevinta | B77: 0 | C77: 0 | D77: 10776
A78: GMarket - equity investment | B78: 0 | C78: 0 | D78: 728
A79: Cash, cash equivalents and restricted cash at end of period | B79: 322 | C79: 882 | D79: 1406 | E79: 2272 | F79: 2493 | G79: 3286
A80: Cash, cash equivalents and restricted cash of continuing operations at end of period | B80: 659 | C80: 1238
A81: Cash and cash equivalents of discontinued operations | B81: -337 | C81: -356 | D81: 1406 | E81: 2272 | F81: 2493 | G81: 3286
A82: Cash and cash equivalents of discontinued operations - Enterprise
A83: Cash and cash equivalents of discontinued operations - PayPal
A84: Cash and cash equivalents | D84: 1379 | E84: 2154 | F84: 1985 | G84: 2433
A85: Customer accounts | D85: 5 | E85: 69 | F85: 481 | G85: 763
A86: Restricted cash included in short-term investments | D86: 22 | E86: 36 | F86: 23 | G86: 88
A87: Restricted cash included in long-term investments | D87: 0 | E87: 13 | F87: 4 | G87: 2
A88: Restricted cash
A89: Restricted cash included in other assets
A90: Restricted cash included in other current assets
A91: All figures in millions of U.S. Dollar.

Sheet Ratios
A1: eBay Inc. (EBAY)
A2: $67.05
B3: DEC '24 | C3: DEC '23 | D3: DEC '22 | E3: DEC '21 | F3: DEC '20 | G3: DEC '19 | H3: DEC '18 | I3: DEC '17 | J3: DEC '16 | K3: DEC '15
F4: Restate | G4: Restate | I4: Restate
A5: Profitability
A6: Gross Margin | B6: 72.042179 | C6: 71.728321 | D6: 72.294148 | E6: 74.601812 | F6: 79.457146 | G6: 74.704851 | H6: 77.394458 | I6: 77.27775 | J6: 77.224635 | K6: 78.631285
A7: SG&A to Sales | B7: 49.540486 | C7: 51.471758 | D7: 49.311238 | E7: 45.808298 | F7: 49.938056 | G7: 52.998247 | H7: 56.657988 | I7: 54.364641 | J7: 51.408843 | K7: 53.992086
A8: Operating Margin | B8: 22.501693 | C8: 20.256563 | D8: 22.98291 | E8: 28.793515 | F8: 29.51909 | G8: 21.706604 | H8: 20.73647 | I8: 22.913109 | J8: 25.815792 | K8: 24.639199
A9: Pretax Margin | B9: 22.037342 | C9: 36.863564 | D9: -16.582082 | E9: 3.795899 | F9: 37.673161 | G9: 20.444185 | H9: 25.274317 | I9: 22.852838 | J9: 40.661544 | K9: 28.002793
A10: Net Margin | B10: 19.164168 | C10: 27.595465 | D10: -13.195236 | E10: 2.403433 | F10: 28.009911 | G10: 17.720631 | H10: 23.507532 | I10: -10.175791 | J10: 81.133757 | K10: 22.660615
A11: Free Cash Flow Margin | B11: 18.922318 | C11: 19.590294 | D11: 18.694977 | E11: 21.106342 | F11: 22.029508 | G11: 30.286382 | H11: 18.662823 | I11: 24.912104 | J11: 24.501615 | K11: 39.164339
A12: Free Cash Flow Conversion Ratio | B12: 71.832408 | C12: 51.963964 | D12: -103.2967 | E12: 693.25397 | F12: 60.675513 | G12: 139.70976 | H12: 79.390823 | I12: -244.81737 | J12: 30.199039 | K12: 172.82999
A13: Capex To Sales | B13: 4.430686 | C13: 4.534606 | D13: 4.65044 | E13: 4.234621 | F13: 5.214551 | G13: 6.113384 | H13: 6.053561 | I13: 6.690105 | J13: 6.971823 | K13: 7.774674
A14: Return on Assets | B14: 9.666951 | C14: 13.068048 | D14: -5.366922 | E14: 1.097179 | F14: 13.269662 | G14: 7.396385 | H14: 10.359594 | I14: -4.065579 | J14: 34.997118 | K14: 6.189106
A15: Return on Equity | B15: 34.291155 | C15: 48.056109 | D15: -17.065166 | E15: 3.778394 | F15: 77.344114 | G15: 33.132991 | H15: 35.282624 | I15: -10.899505 | J15: 85.130003 | K15: 14.704327
A16: Return on Common Equity | B16: 34.291155 | C16: 48.056109 | D16: -17.065166 | E16: 3.778394 | F16: 77.344114 | G16: 33.132991 | H16: 35.282624 | I16: -10.899505 | J16: 85.130003 | K16: 14.704327
A17: Return on Total Capital | B17: 16.827636 | C17: 13.953488 | D17: 13.136785 | E17: 19.48622 | F17: 22.773482 | G17: 13.882036 | H17: 13.283298 | I17: 12.14493 | J17: 14.110915 | K17: 10.355116
... A19: Cash Flow Return on Invested Capital | B19: 19.322821 | C19: 17.93848 | D19: 14.543343 | E19: 18.122911 | F19: 22.309324 | G19: 25.912211 | H19: 17.011744 | I19: 17.808723 | J19: 17.99828 | K19: 20.145861
A20: Valuation
A21: Price/Sales | B21: 3.00251 | C21: 2.311999 | D21: 2.396713 | E21: 4.135241 | F21: 4.063464 | G21: 3.61311 | H21: 2.5867 | I21: 4.033688 | J21: 3.782755 | K21: 3.901955
A22: Price/Earnings | B22: 15.714974 | C22: 8.402358 | F22: 20.055077 | G22: 17.307324 | H22: 11.007843 | J22: 4.675591 | K22: 19.435604
A23: Price/Book Value | B23: 5.65693 | C23: 3.525883 | D23: 4.33773 | E23: 4.039783 | F23: 9.652065 | G23: 10.015171 | H23: 4.089166 | I23: 4.824754 | J23: 3.062249 | K23: 4.947741
A24: Price/Tangible Book Value | B24: 37.894091 | C24: 11.191831 | D24: 28.804549 | E24: 7.063841 | F24: -46.699728 | G24: -16.888108 | H24: 24.960204 | I24: 12.10928 | J24: 5.436831 | K24: 15.988364
A25: Price/Cash Flow | B25: 12.857063 | C25: 9.583454 | D25: 10.266309 | E25: 16.318404 | F25: 14.915048 | G25: 9.926191 | H25: 10.465527 | I25: 12.763942 | J25: 12.018882 | K25: 8.312819
A26: Price/Free Cash Flow | B26: 15.867561 | C26: 11.801756 | D26: 12.820089 | E26: 19.592408 | F26: 18.445552 | G26: 11.929819 | H26: 13.860174 | I26: 16.191677 | J26: 15.4388 | K26: 9.963031
A27: Dividend Yield (%) | B27: 1.743341 | C27: 2.292526 | D27: 2.122016 | E27: 1.082707 | F27: 1.273632 | G27: 1.550817 | H27: 0 | I27: 0 | J27: 0 | K27: 0
A28: Enterprise Value/EBIT | B28: 13.252558 | C28: 10.684605 | D28: 10.935255 | E28: 13.78271 | F28: 14.826402 | G28: 18.492495 | H28: 13.452937 | I28: 18.845445 | J28: 14.704068 | K28: 15.675163
A29: Enterprise Value/EBITDA | B29: 11.632246 | C29: 8.919893 | D29: 9.088139 | E29: 11.844577 | F29: 12.109691 | G29: 13.813581 | H29: 10.277509 | I29: 14.537186 | J29: 11.441433 | K29: 11.864255
A30: Enterprise Value/Sales | B30: 2.98205 | C30: 2.164334 | D30: 2.51324 | E30: 3.968526 | F30: 4.376619 | G30: 4.014093 | H30: 2.789664 | I30: 4.318077 | J30: 3.795972 | K30: 3.862235
A31: Total Debt/Enterprise Value | B31: 0.255081 | C31: 0.378046 | D31: 0.388208 | E31: 0.226676 | F31: 0.2114 | G31: 0.243793 | H31: 0.307699 | I31: 0.23298 | J31: 0.26288 | K31: 0.204283
A32: Per Share
A33: Sales per Share | B33: 20.632735 | C33: 18.866792 | D33: 17.302867 | E33: 16.081288 | F33: 12.366295 | G33: 9.994159 | H33: 10.851665 | I33: 9.356203 | J33: 7.848776 | K33: 7.042623
A34: EBIT (Operating Income) per Share | B34: 4.642715 | C34: 3.821764 | D34: 3.976703 | E34: 4.630368 | F34: 3.650418 | G34: 2.169393 | H34: 2.250252 | I34: 2.143797 | J34: 2.026224 | K34: 1.735246
A35: EPS (recurring) | B35: 4.020359 | C35: 2.886492 | D35: 1.973477 | E35: 2.343252 | F35: 1.329805 | G35: 1.983411 | H35: 2.55227 | I35: -0.942669 | J35: 6.344668 | K35: 1.409344
A36: EPS (basic) | B36: 3.9818 | C36: 5.2208 | D36: -2.2742 | E36: -3.3405 | F36: 2.5338 | G36: 2.1036 | H36: 2.58 | I36: -0.9558 | J36: 6.41 | K36: 1.43
A37: EPS (diluted) | B37: 3.9421 | C37: 5.1914 | D37: -2.2742 | E37: -3.3405 | F37: 2.5056 | G37: 2.0864 | H37: 2.55 | I37: -0.9558 | J37: 6.35 | K37: 1.4139
A38: Dividends per Share | B38: 1.08 | C38: 1 | D38: 0.88 | E38: 0.72 | F38: 0.64 | G38: 0.56 | H38: 0 | I38: 0 | J38: 0 | K38: 0
A39: Dividend Payout Ratio (%) | B39: 27.396565 | C39: 19.262627 | F39: 25.542784 | G39: 26.840491 | H39: 0 | J39: 0 | K39: 0
A40: Book Value per Share | B40: 10.95117 | C40: 12.37137 | D40: 9.5603 | E40: 16.46128 | F40: 5.20614 | G40: 3.60553 | H40: 6.86448 | I40: 7.82216 | J40: 9.69549 | K40: 5.55405
A41: Tangible Book Value per Share | B41: 1.63482 | C41: 3.897485 | D41: 1.439703 | E41: 9.414141 | F41: -1.076023 | G41: -2.138191 | H41: 1.12459 | I41: 3.116618 | J41: 5.460902 | K41: 1.71875
A42: Cash Flow per Share | B42: 4.818363 | C42: 4.551595 | D42: 4.039427 | E42: 4.075153 | F42: 3.369081 | G42: 3.63785 | H42: 2.682139 | I42: 2.956767 | J42: 2.47028 | K42: 3.305738
A43: Free Cash Flow per Share | B43: 3.904192 | C43: 3.69606 | D43: 3.234767 | E43: 3.394172 | F43: 2.724234 | G43: 3.026869 | H43: 2.025227 | I43: 2.330827 | J43: 1.923077 | K43: 2.758197
A44: Diluted Shares Outstanding (M) | B44: 501 | C44: 533 | D44: 558 | E44: 652 | F44: 718 | G44: 856 | H44: 991 | I44: 1064 | J44: 1144 | K44: 1220
A45: Basic Shares Outstanding (M) | B45: 496 | C45: 530 | D45: 558 | E45: 652 | F45: 710 | G45: 849 | H45: 980 | I45: 1064 | J45: 1133 | K45: 1208
A46: Total Shares Outstanding (M) | B46: 471 | C46: 517 | D46: 539 | E46: 594 | F46: 684 | G46: 796 | H46: 915 | I46: 1029 | J46: 1087 | K46: 1184
A47: Asset Turnover Analysis
A48: Cash & ST Investments | B48: 1.357363 | C48: 1.217286 | D48: 1.30209 | E48: 1.938794 | F48: 2.84401 | G48: 2.231933 | H48: 1.995546 | I48: 1.530126 | J48: 1.352259 | K48: 1.230417
A49: Receivables | B49: 9.602415 | C49: 9.221458 | D49: 11.009122 | E49: 14.654088 | F49: 9.693231 | G49: 6.678376 | H49: 7.849635 | I49: 7.838583 | J49: 7.727194 | K49: 9.864524
A50: Current Assets | B50: 1.112522 | C50: 0.990446 | D50: 1.049399 | E50: 1.286424 | F50: 1.492771 | G50: 1.446078 | H50: 1.446402 | I50: 1.198026 | J50: 1.070266 | K50: 0.499027
A51: Fixed Assets | B51: 6.034442 | C51: 5.767709 | D51: 5.894383 | E51: 6.458269 | F51: 4.7166 | G51: 4.700549 | H51: 6.733876 | I51: 6.39576 | J51: 5.849511 | K51: 5.652632
A52: Total Assets | B52: 0.504428 | C52: 0.473558 | D52: 0.406732 | E52: 0.456505 | F52: 0.473749 | G52: 0.417388 | H52: 0.440693 | I52: 0.399534 | J52: 0.431351 | K52: 0.273122
A53: DuPont Analysis
A54: Asset Turnover (x) | B54: 0.504428 | C54: 0.473558 | D54: 0.406732 | E54: 0.456505 | F54: 0.473749 | G54: 0.417388 | H54: 0.440693 | I54: 0.399534 | J54: 0.431351 | K54: 0.273122
A55: x Pretax Margin (%) | B55: 22.037342 | C55: 36.863564 | D55: -16.582082 | E55: 3.795899 | F55: 37.673161 | G55: 20.444185 | H55: 25.274317 | I55: 22.852838 | J55: 40.661544 | K55: 28.002793
A56: = Pretax Return on Assets (%) | B56: 11.116262 | C56: 17.457028 | D56: -6.74446 | E56: 1.732846 | F56: 17.847615 | G56: 8.533164 | H56: 11.138203 | I56: 9.130496 | J56: 17.539393 | K56: 7.648171
A57: x Tax Rate Complement (1-Tax Rate) (%) | B57: 86.962248 | C57: 74.858376 | E57: 63.316583 | F57: 74.349776 | G57: 86.678102 | H57: 93.009566 | I57: -44.527473 | J57: 199.53437 | K57: 80.922693
A58: = Return on Assets (%) | B58: 9.666951 | C58: 13.068048 | D58: -5.366922 | E58: 1.097179 | F58: 13.269662 | G58: 7.396385 | H58: 10.359594 | I58: -4.065579 | J58: 34.997118 | K58: 6.189106
A59: x Equity Multiplier (Assets/Equity) | B59: 3.547256 | C59: 3.677375 | D59: 3.179693 | E59: 3.443736 | F59: 5.828643 | G59: 4.47962 | H59: 3.405792 | I59: 2.680923 | J59: 2.432486 | K59: 2.37584
A60: = Return on Equity (%) | B60: 34.291155 | C60: 48.056109 | D60: -17.065166 | E60: 3.778394 | F60: 77.344114 | G60: 33.132991 | H60: 35.282624 | I60: -10.899505 | J60: 85.130003 | K60: 14.704327
A61: x Earnings Retention (1-Payout) (%) | B61: 72.603435 | C61: 80.737373 | F61: 74.457216 | G61: 73.159509 | H61: 100 | J61: 100 | K61: 100
A62: = Reinvestment Rate (%) | B62: 25.064913 | C62: 38.91246 | D62: -23.615297 | E62: -3.208636 | F62: 63.442699 | G62: 22.795323 | H62: 35.282624 | I62: -10.899505 | J62: 85.130003 | K62: 14.704327
A63: Note: EBIT Return on Assets (%) | B63: 11.350494 | C63: 9.592654 | D63: 9.347881 | E63: 13.144375 | F63: 13.984633 | G63: 9.060083 | H63: 9.138408 | I63: 9.154576 | J63: 11.135665 | K63: 6.729501
A64: Note: Interest as % Assets | B64: 1.337464 | C64: 1.216466 | D64: 1.127098 | E64: 1.010291 | F64: 1.574314 | G64: 1.711236 | H64: 1.428634 | I64: 1.123682 | J64: 0.943515 | K64: 0.809671
A65: Operating Efficiency
A66: Revenue/Employee (actual) | B66: 898869.57 | C66: 817560.98 | D66: 832327.59 | E66: 970833.33 | G66: 643233.08 | H66: 768142.86 | J66: 712619.05 | K66: 740689.66
A67: Net Income/Employee (actual) | B67: 172260.87 | C67: 225609.76 | D67: -109827.59 | E67: 23333.333 | G67: 113984.96 | H67: 180571.43 | J67: 578174.6 | K67: 167844.83
A68: Assets/Employee (actual) | B68: 1683913 | C68: 1757723.6 | D68: 1797413.8 | E68: 2465370.4 | G68: 1366466.2 | H68: 1629928.6 | J68: 1892619 | K68: 1533189.7
A69: Receivables Turnover | B69: 9.602415 | C69: 9.221458 | D69: 11.009122 | E69: 14.654088 | F69: 9.693231 | G69: 6.678376 | H69: 7.849635 | I69: 7.838583 | J69: 7.727194 | K69: 9.864524
A70: Payables Turnover | B70: 2.2265 | C70: 2.4196 | D70: 2.6777 | E70: 3.2755 | F70: 2.3074 | G70: 2.2887 | H70: 2.5244 | I70: 2.5617 | J70: 2.5123 | K70: 3.9569
A71: Asset Turnover | B71: 0.504428 | C71: 0.473558 | D71: 0.406732 | E71: 0.456505 | F71: 0.473749 | G71: 0.417388 | H71: 0.440693 | I71: 0.399534 | J71: 0.431351 | K71: 0.273122
A72: Working Capital Turnover | B72: 7.03676 | C72: 1.54803 | D72: 1.92369 | E72: 2.33571 | F72: 2.785132 | G72: 13.367188 | H72: 4.024701 | I72: 2.378734 | J72: 1.7858 | K72: 1.523134
A73: Operating Cycle - Days
A74: Days of Inventory on Hand
A75: + Days of Sales Outstanding | B75: 38.01127 | C75: 39.581593 | D75: 33.154324 | E75: 24.907725 | F75: 37.655141 | G75: 54.654004 | H75: 46.498977 | I75: 46.56454 | J75: 47.235772 | K75: 37.00128
A76: = Operating Cycle
A77: - Days of Payables Outstanding | B77: 163.93443 | C77: 150.85138 | D77: 136.31101 | E77: 111.43337 | F77: 158.1867 | G77: 159.47918 | H77: 144.58881 | I77: 142.48351 | J77: 145.2852 | K77: 92.243928
A78: Liquidity
A79: Current Ratio (x) | B79: 1.240899 | C79: 2.437168 | D79: 2.175135 | E79: 1.971225 | F79: 1.796602 | G79: 1.157403 | H79: 1.59991 | I79: 2.175892 | J79: 2.306992 | K79: 3.492709
A80: Quick Ratio (x) | B80: 1.240899 | C80: 2.437168 | D80: 2.175135 | E80: 1.971225 | F80: 1.796602 | G80: 1.157403 | H80: 1.59991 | I80: 2.175892 | J80: 2.306992 | K80: 3.492709
A81: Cash Ratio | B81: 1.019351 | C81: 1.994469 | D81: 1.757668 | E81: 1.584379 | F81: 0.872814 | G81: 0.676586 | H81: 1.103502 | I81: 1.647373 | J81: 1.858331 | K81: 2.709236
A82: Cash & ST Inv/Current Assets | B82: 82.146161 | C82: 81.835512 | D82: 80.80732 | E82: 80.37537 | F82: 48.581363 | G82: 58.457289 | H82: 68.972776 | I82: 75.710227 | J82: 80.552113 | K82: 77.56832
A83: CFO/Current Liabilities | B83: 39.58675 | C83: 53.672566 | D83: 52.774526 | E83: 57.485937 | F83: 60.444778 | G83: 76.586326 | H83: 59.676695 | I83: 88.395617 | J83: 73.459839 | K83: 178.21476
A84: Coverage
A85: Net Debt/EBITDA | B85: 0.456226 | C85: -0.529508 | D85: 0.510861 | E85: 0.500712 | F85: 1.325335 | G85: 2.014079 | H85: 1.478589 | I85: 1.404126 | J85: 0.607922 | K85: 0.231677
A86: Net Debt/(EBITDA-Capex) | B86: 0.751369 | C86: -0.396673 | D86: 0.861324 | E86: 0.687195 | F86: 1.719592 | G86: 2.863474 | H86: 1.902998 | I86: 1.812309 | J86: 0.769656 | K86: 0.304368
A87: Total Debt/EBITDA | B87: 2.801887 | C87: 3.165164 | D87: 3.322472 | E87: 2.585255 | F87: 2.413836 | G87: 3.120676 | H87: 3.162384 | I87: 3.386879 | J87: 3.007721 | K87: 2.423668
A88: EBIT/Interest Expense (Int. Coverage) | B88: 8.980695 | C88: 7.745247 | D88: 9.442553 | E88: 11.223048 | F88: 8.621711 | G88: 5.971061 | H88: 6.840491 | I88: 7.811644 | J88: 10.302222 | K88: 14.701389
A89: EBITDA/Interest Expense | B89: 10.23166 | C89: 9.277567 | D89: 11.361702 | E89: 13.05948 | F89: 10.555921 | G89: 7.993569 | H89: 8.953988 | I89: 10.126712 | J89: 13.24 | K89: 19.423611
A90: Fixed-charge Coverage Ratio | B90: 8.980695 | C90: 7.745247 | D90: 9.442553 | E90: 11.223048 | F90: 8.621711 | G90: 5.971061 | H90: 6.840491 | I90: 7.811644 | J90: 10.302222 | K90: 14.701389
A91: CFO/Interest Expense | B91: 9.320463 | C91: 9.224335 | D91: 9.591489 | E91: 9.877323 | F91: 7.957237 | G91: 10.012862 | H91: 8.153374 | I91: 10.773973 | J91: 12.56 | K91: 28.006944
A92: Cash Dividend Coverage Ratio | B92: 4.592871 | C92: 4.772727 | D92: 5.380368 | E92: 5.98927 | F92: 5.903803 | G92: 6.940803
A93: LT Debt/EBITDA | B93: 2.291321 | C93: 3.016393 | D93: 3.048315 | E93: 2.256476 | F93: 2.510439 | G93: 2.895817 | H93: 2.632751 | I93: 3.12276 | J93: 2.520645 | K93: 2.423668
A94: Net Debt/FFO | B94: 0.672794 | C94: -0.312302 | D94: 0.7271 | E94: 0.755643 | F94: 1.789314 | G94: 1.712154 | H94: 1.334158 | I94: 2.047337 | J94: 0.645403 | K94: 0.15656
A95: LT Debt/FFO | B95: 2.480392 | C95: 2.920635 | D95: 3.093501 | E95: 2.840201 | F95: 3.052671 | G95: 2.192811 | H95: 2.37558 | I95: 4.553254 | J95: 2.676051 | K95: 1.637835
A96: FCF/Total Debt | B96: 0.24876 | C96: 0.239426 | D96: 0.191614 | E96: 0.234627 | F96: 0.238101 | G96: 0.309484 | H96: 0.21742 | I96: 0.247629 | J96: 0.245536 | K96: 0.496386
A97: CFO/Total Debt | B97: 0.307008 | C97: 0.294847 | D97: 0.239278 | E97: 0.281701 | F97: 0.294461 | G97: 0.371954 | H97: 0.287943 | I97: 0.314129 | J97: 0.315402 | K97: 0.594926
A98: Total Debt/EBIT | B98: 3.192175 | C98: 3.79136 | D98: 3.997747 | E98: 3.008281 | F98: 2.955361 | G98: 4.177706 | H98: 4.139462 | I98: 4.390618 | J98: 3.865401 | K98: 3.202173
A99: Net Debt/EBIT | B99: 0.519776 | C99: -0.634266 | D99: 0.614691 | E99: 0.582643 | F99: 1.622663 | G99: 2.696284 | H99: 1.935426 | I99: 1.820254 | J99: 0.781277 | K99: 0.306094
A100: EBITDA-Capex/Interest Expense | B100: 8.46332 | C100: 7.543726 | D100: 9.451064 | E100: 11.408922 | F100: 9.032895 | G100: 6.311897 | H100: 6.957055 | I100: 7.84589 | J100: 10.457778 | K100: 14.784722
A101: Leverage
...

Sheet CAPM and WACC
A1: Risk Free Rate | B1: ='10YR Treasury'!E69*12 -> 0.027880048
A2: EBAY Beta | B2: ='Excess Return Analysis'!I23 -> 1.3555671
A3: MRP | B3: 0.04
A5: CAPM | B5: =B1+B2*B3 -> 0.082102733
A7: WACC | B7: 0.0769 | C7: Factset
